<HSoThueDTu>
	<Static GroupName="TKhaiThue">
		<maTKhai>260</maTKhai>
		<tenTKhai>Thông báo phát hành biên lai thu phí, lệ phí</tenTKhai>
		<moTaBMau></moTaBMau>
	</Static>
	<Dynamic GroupName="BienLai">
		<ChiTietBienLai id="id">
			<kyHieuMau>J_35</kyHieuMau>
			<tenBienLai>D_35</tenBienLai>
			<kyHieu>L_35</kyHieu>
			<soLuong>N_35</soLuong>
			<tuSoDenSo></tuSoDenSo>
			<ngayBDauSDung>T_35</ngayBDauSDung>
			<DoanhNghiepIn>
				<mst TINType="1">AE_35</mst>
				<ten>AD_35</ten>
			</DoanhNghiepIn>
			<HopDongDatIn>
				<so></so>
				<ngay></ngay>
			</HopDongDatIn>
		</ChiTietBienLai>
	</Dynamic>
	<Static GroupName="CTieuTKhaiChinh">
		<tenCQTTNhanTBao>K_44</tenCQTTNhanTBao>
		<ngayKy>AA_44</ngayKy>
		<thuTruongDonVi>AA_46</thuTruongDonVi>
	</Static>
</HSoThueDTu>
