<HSoKhaiThue>
	<Static GroupName="TKhaiThue">
		<maTKhai>52</maTKhai>
		<tenTKhai>Báo cáo tài chính bộ 99 BCTC</tenTKhai>
		<moTaBMau/>
	</Static>
	<Static GroupName="GiaHan">
		<maLyDoGiaHan></maLyDoGiaHan>
		<lyDoGiaHan></lyDoGiaHan>
	</Static>
	<Static GroupName="NNT">
		<maHuyenNNT></maHuyenNNT>
		<maTinhNNT></maTinhNNT>
	</Static>
	<Static GroupName="DLyThue">
		<maHuyenDLyThue></maHuyenDLyThue>
		<maTinhDLyThue></maTinhDLyThue>
	</Static>

	<Static GroupName="SoNamNay">
		<ct100_nNay>R_40</ct100_nNay>
		<ct110_nNay>R_41</ct110_nNay>
		<ct111_nNay>R_42</ct111_nNay>
		<ct112_nNay>R_43</ct112_nNay>
		<ct113_nNay>R_44</ct113_nNay>
		<ct114_nNay>R_45</ct114_nNay>
		<ct115_nNay>R_46</ct115_nNay>
		<ct116_nNay>R_47</ct116_nNay>
		<ct120_nNay>R_48</ct120_nNay>
		<ct121_nNay>R_49</ct121_nNay>
		<ct122_nNay>R_50</ct122_nNay>
		<ct123_nNay>R_51</ct123_nNay>
		<ct124_nNay>R_52</ct124_nNay>
		<ct125_nNay>R_53</ct125_nNay>
		<ct126_nNay>R_54</ct126_nNay>
		<ct130_nNay>R_55</ct130_nNay>
		<ct131_nNay>R_56</ct131_nNay>
		<ct132_nNay>R_57</ct132_nNay>
		<ct133_nNay>R_58</ct133_nNay>
		<ct134_nNay>R_59</ct134_nNay>
		<ct135_nNay>R_60</ct135_nNay>
		<ct136_nNay>R_61</ct136_nNay>
		<ct137_nNay>R_62</ct137_nNay>
		<ct138_nNay>R_63</ct138_nNay>
		<ct140_nNay>R_64</ct140_nNay>
		<ct141_nNay>R_65</ct141_nNay>
		<ct142_nNay>R_66</ct142_nNay>
		<ct143_nNay>R_67</ct143_nNay>
		<ct150_nNay>R_68</ct150_nNay>
		<ct151_nNay>R_69</ct151_nNay>
		<ct152_nNay>R_70</ct152_nNay>
		<ct153_nNay>R_71</ct153_nNay>
		<ct154_nNay>R_73</ct154_nNay>
		<ct155_nNay>R_74</ct155_nNay>
		<ct156_nNay>R_75</ct156_nNay>
		<ct200_nNay>R_76</ct200_nNay>
		<ct210_nNay>R_77</ct210_nNay>
		<ct211_nNay>R_78</ct211_nNay>
		<ct212_nNay>R_79</ct212_nNay>
		<ct213_nNay>R_80</ct213_nNay>
		<ct214_nNay>R_81</ct214_nNay>
		<ct215_nNay>R_82</ct215_nNay>
		<ct216_nNay>R_83</ct216_nNay>
		<ct217_nNay>R_84</ct217_nNay>
		<ct218_nNay>R_85</ct218_nNay>
		<ct219_nNay>R_86</ct219_nNay>
		<ct220_nNay>R_87</ct220_nNay>
		<ct221_nNay>R_88</ct221_nNay>
		<ct222_nNay>R_89</ct222_nNay>
		<ct223_nNay>R_90</ct223_nNay>
		<ct224_nNay>R_91</ct224_nNay>
		<ct225_nNay>R_92</ct225_nNay>
		<ct226_nNay>R_93</ct226_nNay>
		<ct227_nNay>R_94</ct227_nNay>
		<ct230_nNay>R_95</ct230_nNay>
		<ct240_nNay>R_96</ct240_nNay>
		<ct241_nNay>R_97</ct241_nNay>
		<ct242_nNay>R_98</ct242_nNay>
		<ct243_nNay>R_99</ct243_nNay>
		<ct250_nNay>R_100</ct250_nNay>
		<ct300_nNay>R_102</ct300_nNay>
		<ct310_nNay>R_103</ct310_nNay>
		<ct311_nNay>R_104</ct311_nNay>
		<ct312_nNay>R_106</ct312_nNay>
		<ct313_nNay>R_107</ct313_nNay>
		<ct314_nNay>R_108</ct314_nNay>
		<ct315_nNay>R_109</ct315_nNay>
		<ct316_nNay>R_110</ct316_nNay>
		<ct317_nNay>R_111</ct317_nNay>
		<ct318_nNay>R_112</ct318_nNay>
		<ct319_nNay>R_113</ct319_nNay>
		<ct320_nNay>R_114</ct320_nNay>
		<ct321_nNay>R_116</ct321_nNay>
		<ct322_nNay>R_117</ct322_nNay>
		<ct323_nNay>R_118</ct323_nNay>
		<ct324_nNay>R_119</ct324_nNay>
		<ct325_nNay>R_120</ct325_nNay>
		<ct326_nNay>R_121</ct326_nNay>
		<ct327_nNay>R_122</ct327_nNay>
		<ct328_nNay>R_123</ct328_nNay>
		<ct329_nNay>R_124</ct329_nNay>
		<ct330_nNay>R_125</ct330_nNay>
		<ct331_nNay>R_126</ct331_nNay>
		<ct332_nNay>R_127</ct332_nNay>
		<ct340_nNay>R_128</ct340_nNay>
		<ct341_nNay>R_129</ct341_nNay>
		<ct342_nNay>R_130</ct342_nNay>
		<ct343_nNay>R_131</ct343_nNay>
		<ct344_nNay>R_132</ct344_nNay>
		<ct345_nNay>R_133</ct345_nNay>
		<ct400_nNay>R_134</ct400_nNay>
		<ct410_nNay>R_135</ct410_nNay>
		<ct411_nNay>R_136</ct411_nNay>
		<ct412_nNay>R_137</ct412_nNay>
		<ct413_nNay>R_139</ct413_nNay>
		<ct414_nNay>R_140</ct414_nNay>
		<ct420_nNay>R_141</ct420_nNay>
		<ct421_nNay>R_142</ct421_nNay>
		<ct422_nNay>R_143</ct422_nNay>
		<ct423_nNay>R_144</ct423_nNay>
		<ct430_nNay>R_145</ct430_nNay>
		<ct431_nNay>R_146</ct431_nNay>
		<ct432_nNay>R_147</ct432_nNay>
		<ct433_nNay>R_149</ct433_nNay>
		<ct434_nNay>R_150</ct434_nNay>
		<ct435_nNay>R_151</ct435_nNay>
		<ct436_nNay>R_152</ct436_nNay>
		<ct437_nNay>R_153</ct437_nNay>
		<ct438_nNay>R_154</ct438_nNay>
		<ct439_nNay>R_155</ct439_nNay>
		<ct440_nNay>R_156</ct440_nNay>
		<ct441_nNay>R_157</ct441_nNay>
		<ct442_nNay>R_158</ct442_nNay>
		<ct443_nNay>R_159</ct443_nNay>
		<ct444_nNay>R_160</ct444_nNay>
		<ct445_nNay>R_161</ct445_nNay>
		<ct450_nNay>R_162</ct450_nNay>
		<nBangCDKT_nNay>R_163</nBangCDKT_nNay>
		<ct001_nNay>R_164</ct001_nNay>
		<ct002_nNay>R_165</ct002_nNay>
		<ct003_nNay>R_166</ct003_nNay>
		<ct004_nNay>R_167</ct004_nNay>
		<ct005_nNay>R_168</ct005_nNay>
		<ct006_nNay>R_169</ct006_nNay>
		<ct007_nNay>R_171</ct007_nNay>
		<ct008_nNay>R_172</ct008_nNay>
		<ct009_nNay>R_173</ct009_nNay>
		<ct010_nNay>R_174</ct010_nNay>
		<ct011_nNay>R_175</ct011_nNay>
		<ct012_nNay>R_176</ct012_nNay>
		<ct013_nNay>R_177</ct013_nNay>
		<ct014_nNay>R_178</ct014_nNay>
		<ct015_nNay>R_179</ct015_nNay>
		<ct016_nNay>R_180</ct016_nNay>
		<ct017_nNay>R_181</ct017_nNay>
		<ct018_nNay>R_182</ct018_nNay>
		<ct019_nNay>R_183</ct019_nNay>
		<ct020_nNay>R_184</ct020_nNay>
		<ct021_nNay>R_185</ct021_nNay>
		<ct022_nNay>R_186</ct022_nNay>
		<ct023_nNay>R_187</ct023_nNay>
		<trongDo_nNay>R_188</trongDo_nNay>
		<ct024_nNay>R_189</ct024_nNay>
		<ct025_nNay>R_190</ct025_nNay>
		<ct026_nNay>R_191</ct026_nNay>
		<ct027_nNay>R_192</ct027_nNay>
		<ct028_nNay>R_193</ct028_nNay>
		<ct029_nNay>R_194</ct029_nNay>
		<ct030_nNay>R_195</ct030_nNay>
		<ct031_nNay>R_196</ct031_nNay>
		<ct032_nNay>R_197</ct032_nNay>
		<ct033_nNay>R_198</ct033_nNay>
		<ct034_nNay>R_199</ct034_nNay>
		<ct035_nNay>R_200</ct035_nNay>
		<ct036_nNay>R_201</ct036_nNay>
		<ct037_nNay>R_202</ct037_nNay>
		<ct038_nNay>R_203</ct038_nNay>
		<ct039_nNay>R_204</ct039_nNay>
		<ct040_nNay>R_205</ct040_nNay>
		<ct041_nNay>R_206</ct041_nNay>
		<ct042_nNay>R_207</ct042_nNay>
		<ct043_nNay>R_208</ct043_nNay>
	</Static>
	<Static GroupName="SoNamNgoai">
		<ct100_nNgoai>W_40</ct100_nNgoai>
		<ct110_nNgoai>W_41</ct110_nNgoai>
		<ct111_nNgoai>W_42</ct111_nNgoai>
		<ct112_nNgoai>W_43</ct112_nNgoai>
		<ct113_nNgoai>W_44</ct113_nNgoai>
		<ct114_nNgoai>W_45</ct114_nNgoai>
		<ct115_nNgoai>W_46</ct115_nNgoai>
		<ct116_nNgoai>W_47</ct116_nNgoai>
		<ct120_nNgoai>W_48</ct120_nNgoai>
		<ct121_nNgoai>W_49</ct121_nNgoai>
		<ct122_nNgoai>W_50</ct122_nNgoai>
		<ct123_nNgoai>W_51</ct123_nNgoai>
		<ct124_nNgoai>W_52</ct124_nNgoai>
		<ct125_nNgoai>W_53</ct125_nNgoai>
		<ct126_nNgoai>W_54</ct126_nNgoai>
		<ct130_nNgoai>W_55</ct130_nNgoai>
		<ct131_nNgoai>W_56</ct131_nNgoai>
		<ct132_nNgoai>W_57</ct132_nNgoai>
		<ct133_nNgoai>W_58</ct133_nNgoai>
		<ct134_nNgoai>W_59</ct134_nNgoai>
		<ct135_nNgoai>W_60</ct135_nNgoai>
		<ct136_nNgoai>W_61</ct136_nNgoai>
		<ct137_nNgoai>W_62</ct137_nNgoai>
		<ct138_nNgoai>W_63</ct138_nNgoai>
		<ct140_nNgoai>W_64</ct140_nNgoai>
		<ct141_nNgoai>W_65</ct141_nNgoai>
		<ct142_nNgoai>W_66</ct142_nNgoai>
		<ct143_nNgoai>W_67</ct143_nNgoai>
		<ct150_nNgoai>W_68</ct150_nNgoai>
		<ct151_nNgoai>W_69</ct151_nNgoai>
		<ct152_nNgoai>W_70</ct152_nNgoai>
		<ct153_nNgoai>W_71</ct153_nNgoai>
		<ct154_nNgoai>W_73</ct154_nNgoai>
		<ct155_nNgoai>W_74</ct155_nNgoai>
		<ct156_nNgoai>W_75</ct156_nNgoai>
		<ct200_nNgoai>W_76</ct200_nNgoai>
		<ct210_nNgoai>W_77</ct210_nNgoai>
		<ct211_nNgoai>W_78</ct211_nNgoai>
		<ct212_nNgoai>W_79</ct212_nNgoai>
		<ct213_nNgoai>W_80</ct213_nNgoai>
		<ct214_nNgoai>W_81</ct214_nNgoai>
		<ct215_nNgoai>W_82</ct215_nNgoai>
		<ct216_nNgoai>W_83</ct216_nNgoai>
		<ct217_nNgoai>W_84</ct217_nNgoai>
		<ct218_nNgoai>W_85</ct218_nNgoai>
		<ct219_nNgoai>W_86</ct219_nNgoai>
		<ct220_nNgoai>W_87</ct220_nNgoai>
		<ct221_nNgoai>W_88</ct221_nNgoai>
		<ct222_nNgoai>W_89</ct222_nNgoai>
		<ct223_nNgoai>W_90</ct223_nNgoai>
		<ct224_nNgoai>W_91</ct224_nNgoai>
		<ct225_nNgoai>W_92</ct225_nNgoai>
		<ct226_nNgoai>W_93</ct226_nNgoai>
		<ct227_nNgoai>W_94</ct227_nNgoai>
		<ct230_nNgoai>W_95</ct230_nNgoai>
		<ct240_nNgoai>W_96</ct240_nNgoai>
		<ct241_nNgoai>W_97</ct241_nNgoai>
		<ct242_nNgoai>W_98</ct242_nNgoai>
		<ct243_nNgoai>W_99</ct243_nNgoai>
		<ct250_nNgoai>W_100</ct250_nNgoai>
		<ct300_nNgoai>W_102</ct300_nNgoai>
		<ct310_nNgoai>W_103</ct310_nNgoai>
		<ct311_nNgoai>W_104</ct311_nNgoai>
		<ct312_nNgoai>W_106</ct312_nNgoai>
		<ct313_nNgoai>W_107</ct313_nNgoai>
		<ct314_nNgoai>W_108</ct314_nNgoai>
		<ct315_nNgoai>W_109</ct315_nNgoai>
		<ct316_nNgoai>W_110</ct316_nNgoai>
		<ct317_nNgoai>W_111</ct317_nNgoai>
		<ct318_nNgoai>W_112</ct318_nNgoai>
		<ct319_nNgoai>W_113</ct319_nNgoai>
		<ct320_nNgoai>W_114</ct320_nNgoai>
		<ct321_nNgoai>W_116</ct321_nNgoai>
		<ct322_nNgoai>W_117</ct322_nNgoai>
		<ct323_nNgoai>W_118</ct323_nNgoai>
		<ct324_nNgoai>W_119</ct324_nNgoai>
		<ct325_nNgoai>W_120</ct325_nNgoai>
		<ct326_nNgoai>W_121</ct326_nNgoai>
		<ct327_nNgoai>W_122</ct327_nNgoai>
		<ct328_nNgoai>W_123</ct328_nNgoai>
		<ct329_nNgoai>W_124</ct329_nNgoai>
		<ct330_nNgoai>W_125</ct330_nNgoai>
		<ct331_nNgoai>W_126</ct331_nNgoai>
		<ct332_nNgoai>W_127</ct332_nNgoai>
		<ct340_nNgoai>W_128</ct340_nNgoai>
		<ct341_nNgoai>W_129</ct341_nNgoai>
		<ct342_nNgoai>W_130</ct342_nNgoai>
		<ct343_nNgoai>W_131</ct343_nNgoai>
		<ct344_nNgoai>W_132</ct344_nNgoai>
		<ct345_nNgoai>W_133</ct345_nNgoai>
		<ct400_nNgoai>W_134</ct400_nNgoai>
		<ct410_nNgoai>W_135</ct410_nNgoai>
		<ct411_nNgoai>W_136</ct411_nNgoai>
		<ct412_nNgoai>W_137</ct412_nNgoai>
		<ct413_nNgoai>W_139</ct413_nNgoai>
		<ct414_nNgoai>W_140</ct414_nNgoai>
		<ct420_nNgoai>W_141</ct420_nNgoai>
		<ct421_nNgoai>W_142</ct421_nNgoai>
		<ct422_nNgoai>W_143</ct422_nNgoai>
		<ct423_nNgoai>W_144</ct423_nNgoai>
		<ct430_nNgoai>W_145</ct430_nNgoai>
		<ct431_nNgoai>W_146</ct431_nNgoai>
		<ct432_nNgoai>W_147</ct432_nNgoai>
		<ct433_nNgoai>W_149</ct433_nNgoai>
		<ct434_nNgoai>W_150</ct434_nNgoai>
		<ct435_nNgoai>W_151</ct435_nNgoai>
		<ct436_nNgoai>W_152</ct436_nNgoai>
		<ct437_nNgoai>W_153</ct437_nNgoai>
		<ct438_nNgoai>W_154</ct438_nNgoai>
		<ct439_nNgoai>W_155</ct439_nNgoai>
		<ct440_nNgoai>W_156</ct440_nNgoai>
		<ct441_nNgoai>W_157</ct441_nNgoai>
		<ct442_nNgoai>W_158</ct442_nNgoai>
		<ct443_nNgoai>W_159</ct443_nNgoai>
		<ct444_nNgoai>W_160</ct444_nNgoai>
		<ct445_nNgoai>W_161</ct445_nNgoai>
		<ct450_nNgoai>W_162</ct450_nNgoai>
		<nBangCDKT_nNgoai>W_163</nBangCDKT_nNgoai>
		<ct001_nNgoai>W_164</ct001_nNgoai>
		<ct002_nNgoai>W_165</ct002_nNgoai>
		<ct003_nNgoai>W_166</ct003_nNgoai>
		<ct004_nNgoai>W_167</ct004_nNgoai>
		<ct005_nNgoai>W_168</ct005_nNgoai>
		<ct006_nNgoai>W_169</ct006_nNgoai>
		<ct007_nNgoai>W_171</ct007_nNgoai>
		<ct008_nNgoai>W_172</ct008_nNgoai>
		<ct009_nNgoai>W_173</ct009_nNgoai>
		<ct010_nNgoai>W_174</ct010_nNgoai>
		<ct011_nNgoai>W_175</ct011_nNgoai>
		<ct012_nNgoai>W_176</ct012_nNgoai>
		<ct013_nNgoai>W_177</ct013_nNgoai>
		<ct014_nNgoai>W_178</ct014_nNgoai>
		<ct015_nNgoai>W_179</ct015_nNgoai>
		<ct016_nNgoai>W_180</ct016_nNgoai>
		<ct017_nNgoai>W_181</ct017_nNgoai>
		<ct018_nNgoai>W_182</ct018_nNgoai>
		<ct019_nNgoai>W_183</ct019_nNgoai>
		<ct020_nNgoai>W_184</ct020_nNgoai>
		<ct021_nNgoai>W_185</ct021_nNgoai>
		<ct022_nNgoai>W_186</ct022_nNgoai>
		<ct023_nNgoai>W_187</ct023_nNgoai>
		<trongDo_nNgoai>W_188</trongDo_nNgoai>
		<ct024_nNgoai>W_189</ct024_nNgoai>
		<ct025_nNgoai>W_190</ct025_nNgoai>
		<ct026_nNgoai>W_191</ct026_nNgoai>
		<ct027_nNgoai>W_192</ct027_nNgoai>
		<ct028_nNgoai>W_193</ct028_nNgoai>
		<ct029_nNgoai>W_194</ct029_nNgoai>
		<ct030_nNgoai>W_195</ct030_nNgoai>
		<ct031_nNgoai>W_196</ct031_nNgoai>
		<ct032_nNgoai>W_197</ct032_nNgoai>
		<ct033_nNgoai>W_198</ct033_nNgoai>
		<ct034_nNgoai>W_199</ct034_nNgoai>
		<ct035_nNgoai>W_200</ct035_nNgoai>
		<ct036_nNgoai>W_201</ct036_nNgoai>
		<ct037_nNgoai>W_202</ct037_nNgoai>
		<ct038_nNgoai>W_203</ct038_nNgoai>
		<ct039_nNgoai>W_204</ct039_nNgoai>
		<ct040_nNgoai>W_205</ct040_nNgoai>
		<ct041_nNgoai>W_206</ct041_nNgoai>
		<ct042_nNgoai>W_207</ct042_nNgoai>
		<ct043_nNgoai>W_208</ct043_nNgoai>
	</Static>
	<Static GroupName="TKhaiThue">
		<nguoiKy>R_210</nguoiKy>
		<ngayKy>R_212</ngayKy>
	</Static>
	<Static GroupName="NVienDLy">
		<tenNVienDLyThue></tenNVienDLyThue>
		<cchiHNghe></cchiHNghe>
	</Static>
</HSoKhaiThue>
