<!-- edited with XML Spy v4.1 U (http://www.xmlspy.com) by CMCSoft-->
<!DOCTYPE Sections SYSTEM "Schema.dtd">
<Sections>
	<Section Dynamic="0" MaxRows="0">
		<Cells>
			<Cell CellID="K_4" Value=""/>
			<Cell CellID="K_5" Value=""/>
			<Cell CellID="K_6" Value=""/>
			<Cell CellID="I_7" Value=""/>
			<Cell CellID="T_7" Value=""/>
			<Cell CellID="AF_7" Value=""/>
			<Cell CellID="I_9" Value=""/>
			<Cell CellID="I_11" Value=""/>
			<Cell CellID="T_11" Value=""/>
			<Cell CellID="AF_11" Value=""/>
			<Cell CellID="T_9" Value="" MaxLen="20" HelpContexID="01_01_M_10"/>
			<Cell CellID="AF_16" Value="" MinValue="0" MaxValue="9999999999" HelpContexID="01_01_V_10"/>
			<Cell CellID="I_13" Value=""/>
			<Cell CellID="T_13" Value="" MaxLen="100" HelpContexID="01_01_M_14"/>
			<Cell CellID="AF_9" Value="" MaxLen="60"/>
		</Cells>
	</Section>
	<Section Dynamic="0" MaxRows="0">
		<Cells>
			<Cell CellID="AN" Value=""/>
		</Cells>
	</Section>
	<Section Dynamic="1" MaxRows="0">
		<Cells>
			<Cell CellID="D_38" FirstCell="0" Value="010101" MCT="2"/>
			<Cell CellID="O_38" Value="Kg" MCT="3"/>
			<Cell CellID="R_38" Value="0.000" MCT="4"/>
			<Cell CellID="U_38" Value="0.00" MCT="5"/>
			<Cell CellID="Z_38" Value="7.0000" MCT="6"/>
			<Cell CellID="AC_38" Value="0" MCT="7"/>
			<Cell CellID="AI_38" Value="0" MCT="9"/>
			<Cell CellID="AF_38" Value="0" MCT="8" Receive="0"/>
			<Cell CellID="AM_38" Value="0" MCT="10" Receive="0"/>
		</Cells>
		<Cells>
			<Cell CellID="D_39" FirstCell="1" Value="010102" MCT="2"/>
			<Cell CellID="O_39" Value="Kg" MCT="3"/>
			<Cell CellID="R_39" Value="0" MCT="4"/>
			<Cell CellID="U_39" Value="0" MCT="5"/>
			<Cell CellID="Z_39" Value="10.0000" MCT="6"/>
			<Cell CellID="AC_39" Value="0" MCT="7"/>
			<Cell CellID="AI_39" Value="0" MCT="9"/>
			<Cell CellID="AF_39" Value="0" MCT="8" Receive="0"/>
			<Cell CellID="AM_39" Value="0" MCT="10" Receive="0"/>
		</Cells>
		<Cells>
			<Cell CellID="D_40" FirstCell="1" Value="010103" MCT="2"/>
			<Cell CellID="O_40" Value="Kg" MCT="3"/>
			<Cell CellID="R_40" Value="0" MCT="4"/>
			<Cell CellID="U_40" Value="0" MCT="5"/>
			<Cell CellID="Z_40" Value="11.0000" MCT="6"/>
			<Cell CellID="AC_40" Value="0" MCT="7"/>
			<Cell CellID="AI_40" Value="0" MCT="9"/>
			<Cell CellID="AF_40" Value="0" MCT="8" Receive="0"/>
			<Cell CellID="AM_40" Value="0" MCT="10" Receive="0"/>
		</Cells>
		<Cells>
			<Cell CellID="D_41" FirstCell="1" Value="010104" MCT="2"/>
			<Cell CellID="O_41" Value="Kg" MCT="3"/>
			<Cell CellID="R_41" Value="0" MCT="4"/>
			<Cell CellID="U_41" Value="0" MCT="5"/>
			<Cell CellID="Z_41" Value="11.0000" MCT="6"/>
			<Cell CellID="AC_41" Value="0" MCT="7"/>
			<Cell CellID="AI_41" Value="0" MCT="9"/>
			<Cell CellID="AF_41" Value="0" MCT="8" Receive="0"/>
			<Cell CellID="AM_41" Value="0" MCT="10" Receive="0"/>
		</Cells>
		<Cells>
			<Cell CellID="D_42" FirstCell="1" Value="010207" MCT="2"/>
			<Cell CellID="O_42" Value="Kg" MCT="3"/>
			<Cell CellID="R_42" Value="0" MCT="4"/>
			<Cell CellID="U_42" Value="0" MCT="5"/>
			<Cell CellID="Z_42" Value="15.0000" MCT="6"/>
			<Cell CellID="AC_42" Value="0" MCT="7"/>
			<Cell CellID="AI_42" Value="0" MCT="9"/>
			<Cell CellID="AF_42" Value="0" MCT="8" Receive="0"/>
			<Cell CellID="AM_42" Value="0" MCT="10" Receive="0"/>
		</Cells>
		<Cells>
			<Cell CellID="D_43" FirstCell="1" Value="010201" MCT="2"/>
			<Cell CellID="O_43" Value="Kg" MCT="3"/>
			<Cell CellID="R_43" Value="0" MCT="4"/>
			<Cell CellID="U_43" Value="0" MCT="5"/>
			<Cell CellID="Z_43" Value="9.0000" MCT="6"/>
			<Cell CellID="AC_43" Value="0" MCT="7"/>
			<Cell CellID="AI_43" Value="0" MCT="9"/>
			<Cell CellID="AF_43" Value="0" MCT="8" Receive="0"/>
			<Cell CellID="AM_43" Value="0" MCT="10" Receive="0"/>
		</Cells>
		<Cells>
			<Cell CellID="D_44" FirstCell="1" Value="010202" MCT="2"/>
			<Cell CellID="O_44" Value="Kg" MCT="3"/>
			<Cell CellID="R_44" Value="0" MCT="4"/>
			<Cell CellID="U_44" Value="0" MCT="5"/>
			<Cell CellID="Z_44" Value="9.0000" MCT="6"/>
			<Cell CellID="AC_44" Value="0" MCT="7"/>
			<Cell CellID="AI_44" Value="0" MCT="9"/>
			<Cell CellID="AF_44" Value="0" MCT="8" Receive="0"/>
			<Cell CellID="AM_44" Value="0" MCT="10" Receive="0"/>
		</Cells>
		<Cells>
			<Cell CellID="D_45" FirstCell="1" Value="010203a" MCT="2"/>
			<Cell CellID="O_45" Value="Kg" MCT="3"/>
			<Cell CellID="R_45" Value="0" MCT="4"/>
			<Cell CellID="U_45" Value="0" MCT="5"/>
			<Cell CellID="Z_45" Value="12.0000" MCT="6"/>
			<Cell CellID="AC_45" Value="0" MCT="7"/>
			<Cell CellID="AI_45" Value="0" MCT="9"/>
			<Cell CellID="AF_45" Value="0" MCT="8" Receive="0"/>
			<Cell CellID="AM_45" Value="0" MCT="10" Receive="0"/>
		</Cells>
		<Cells>
			<Cell CellID="D_46" FirstCell="1" Value="010203b" MCT="2"/>
			<Cell CellID="O_46" Value="Kg" MCT="3"/>
			<Cell CellID="R_46" Value="0" MCT="4"/>
			<Cell CellID="U_46" Value="0" MCT="5"/>
			<Cell CellID="Z_46" Value="15.0000" MCT="6"/>
			<Cell CellID="AC_46" Value="0" MCT="7"/>
			<Cell CellID="AI_46" Value="0" MCT="9"/>
			<Cell CellID="AF_46" Value="0" MCT="8" Receive="0"/>
			<Cell CellID="AM_46" Value="0" MCT="10" Receive="0"/>
		</Cells>
		<Cells>
			<Cell CellID="D_47" FirstCell="1" Value="010204" MCT="2"/>
			<Cell CellID="O_47" Value="Kg" MCT="3"/>
			<Cell CellID="R_47" Value="0" MCT="4"/>
			<Cell CellID="U_47" Value="0" MCT="5"/>
			<Cell CellID="Z_47" Value="7.0000" MCT="6"/>
			<Cell CellID="AC_47" Value="0" MCT="7"/>
			<Cell CellID="AI_47" Value="0" MCT="9"/>
			<Cell CellID="AF_47" Value="0" MCT="8" Receive="0"/>
			<Cell CellID="AM_47" Value="0" MCT="10" Receive="0"/>
		</Cells>
		<Cells>
			<Cell CellID="D_48" FirstCell="1" Value="010208" MCT="2"/>
			<Cell CellID="O_48" Value="Kg" MCT="3"/>
			<Cell CellID="R_48" Value="0" MCT="4"/>
			<Cell CellID="U_48" Value="0" MCT="5"/>
			<Cell CellID="Z_48" Value="10.0000" MCT="6"/>
			<Cell CellID="AC_48" Value="0" MCT="7"/>
			<Cell CellID="AI_48" Value="0" MCT="9"/>
			<Cell CellID="AF_48" Value="0" MCT="8" Receive="0"/>
			<Cell CellID="AM_48" Value="0" MCT="10" Receive="0"/>
		</Cells>
		<Cells>
			<Cell CellID="D_49" FirstCell="1" Value="010209" MCT="2"/>
			<Cell CellID="O_49" Value="Kg" MCT="3"/>
			<Cell CellID="R_49" Value="0" MCT="4"/>
			<Cell CellID="U_49" Value="0" MCT="5"/>
			<Cell CellID="Z_49" Value="10.0000" MCT="6"/>
			<Cell CellID="AC_49" Value="0" MCT="7"/>
			<Cell CellID="AI_49" Value="0" MCT="9"/>
			<Cell CellID="AF_49" Value="0" MCT="8" Receive="0"/>
			<Cell CellID="AM_49" Value="0" MCT="10" Receive="0"/>
		</Cells>
		<Cells>
			<Cell CellID="D_50" FirstCell="1" Value="010210a" MCT="2"/>
			<Cell CellID="O_50" Value="Kg" MCT="3"/>
			<Cell CellID="R_50" Value="0" MCT="4"/>
			<Cell CellID="U_50" Value="0" MCT="5"/>
			<Cell CellID="Z_50" Value="10.0000" MCT="6"/>
			<Cell CellID="AC_50" Value="0" MCT="7"/>
			<Cell CellID="AI_50" Value="0" MCT="9"/>
			<Cell CellID="AF_50" Value="0" MCT="8" Receive="0"/>
			<Cell CellID="AM_50" Value="0" MCT="10" Receive="0"/>
		</Cells>
		<Cells>
			<Cell CellID="D_51" FirstCell="1" Value="010210b" MCT="2"/>
			<Cell CellID="O_51" Value="Kg" MCT="3"/>
			<Cell CellID="R_51" Value="0" MCT="4"/>
			<Cell CellID="U_51" Value="0" MCT="5"/>
			<Cell CellID="Z_51" Value="10.0000" MCT="6"/>
			<Cell CellID="AC_51" Value="0" MCT="7"/>
			<Cell CellID="AI_51" Value="0" MCT="9"/>
			<Cell CellID="AF_51" Value="0" MCT="8" Receive="0"/>
			<Cell CellID="AM_51" Value="0" MCT="10" Receive="0"/>
		</Cells>
		<Cells>
			<Cell CellID="D_52" FirstCell="1" Value="010205" MCT="2"/>
			<Cell CellID="O_52" Value="Kg" MCT="3"/>
			<Cell CellID="R_52" Value="0" MCT="4"/>
			<Cell CellID="U_52" Value="0" MCT="5"/>
			<Cell CellID="Z_52" Value="7.0000" MCT="6"/>
			<Cell CellID="AC_52" Value="0" MCT="7"/>
			<Cell CellID="AI_52" Value="0" MCT="9"/>
			<Cell CellID="AF_52" Value="0" MCT="8" Receive="0"/>
			<Cell CellID="AM_52" Value="0" MCT="10" Receive="0"/>
		</Cells>
		<Cells>
			<Cell CellID="D_53" FirstCell="1" Value="010211" MCT="2"/>
			<Cell CellID="O_53" Value="Kg" MCT="3"/>
			<Cell CellID="R_53" Value="0" MCT="4"/>
			<Cell CellID="U_53" Value="0" MCT="5"/>
			<Cell CellID="Z_53" Value="10.0000" MCT="6"/>
			<Cell CellID="AC_53" Value="0" MCT="7"/>
			<Cell CellID="AI_53" Value="0" MCT="9"/>
			<Cell CellID="AF_53" Value="0" MCT="8" Receive="0"/>
			<Cell CellID="AM_53" Value="0" MCT="10" Receive="0"/>
		</Cells>
		<Cells>
			<Cell CellID="D_54" FirstCell="1" Value="010212" MCT="2"/>
			<Cell CellID="O_54" Value="Kg" MCT="3"/>
			<Cell CellID="R_54" Value="0" MCT="4"/>
			<Cell CellID="U_54" Value="0" MCT="5"/>
			<Cell CellID="Z_54" Value="12.0000" MCT="6"/>
			<Cell CellID="AC_54" Value="0" MCT="7"/>
			<Cell CellID="AI_54" Value="0" MCT="9"/>
			<Cell CellID="AF_54" Value="0" MCT="8" Receive="0"/>
			<Cell CellID="AM_54" Value="0" MCT="10" Receive="0"/>
		</Cells>
		<Cells>
			<Cell CellID="D_55" FirstCell="1" Value="010213" MCT="2"/>
			<Cell CellID="O_55" Value="Kg" MCT="3"/>
			<Cell CellID="R_55" Value="0" MCT="4"/>
			<Cell CellID="U_55" Value="0" MCT="5"/>
			<Cell CellID="Z_55" Value="10.0000" MCT="6"/>
			<Cell CellID="AC_55" Value="0" MCT="7"/>
			<Cell CellID="AI_55" Value="0" MCT="9"/>
			<Cell CellID="AF_55" Value="0" MCT="8" Receive="0"/>
			<Cell CellID="AM_55" Value="0" MCT="10" Receive="0"/>
		</Cells>
		<Cells>
			<Cell CellID="D_56" FirstCell="1" Value="010214" MCT="2"/>
			<Cell CellID="O_56" Value="Kg" MCT="3"/>
			<Cell CellID="R_56" Value="0" MCT="4"/>
			<Cell CellID="U_56" Value="0" MCT="5"/>
			<Cell CellID="Z_56" Value="10.0000" MCT="6"/>
			<Cell CellID="AC_56" Value="0" MCT="7"/>
			<Cell CellID="AI_56" Value="0" MCT="9"/>
			<Cell CellID="AF_56" Value="0" MCT="8" Receive="0"/>
			<Cell CellID="AM_56" Value="0" MCT="10" Receive="0"/>
		</Cells>
		<Cells>
			<Cell CellID="D_57" FirstCell="1" Value="010206" MCT="2"/>
			<Cell CellID="O_57" Value="Kg" MCT="3"/>
			<Cell CellID="R_57" Value="0" MCT="4"/>
			<Cell CellID="U_57" Value="0" MCT="5"/>
			<Cell CellID="Z_57" Value="7.0000" MCT="6"/>
			<Cell CellID="AC_57" Value="0" MCT="7"/>
			<Cell CellID="AI_57" Value="0" MCT="9"/>
			<Cell CellID="AF_57" Value="0" MCT="8" Receive="0"/>
			<Cell CellID="AM_57" Value="0" MCT="10" Receive="0"/>
		</Cells>
		<Cells>
			<Cell CellID="D_58" FirstCell="1" Value="020101" MCT="2"/>
			<Cell CellID="O_58" Value="M3" MCT="3"/>
			<Cell CellID="R_58" Value="0" MCT="4"/>
			<Cell CellID="U_58" Value="0" MCT="5"/>
			<Cell CellID="Z_58" Value="3.0000" MCT="6"/>
			<Cell CellID="AC_58" Value="0" MCT="7"/>
			<Cell CellID="AI_58" Value="0" MCT="9"/>
			<Cell CellID="AF_58" Value="0" MCT="8" Receive="0"/>
			<Cell CellID="AM_58" Value="0" MCT="10" Receive="0"/>
		</Cells>
		<Cells>
			<Cell CellID="D_59" FirstCell="1" Value="020102a" MCT="2"/>
			<Cell CellID="O_59" Value="M3" MCT="3"/>
			<Cell CellID="R_59" Value="0" MCT="4"/>
			<Cell CellID="U_59" Value="0" MCT="5"/>
			<Cell CellID="Z_59" Value="5.0000" MCT="6"/>
			<Cell CellID="AC_59" Value="0" MCT="7"/>
			<Cell CellID="AI_59" Value="0" MCT="9"/>
			<Cell CellID="AF_59" Value="0" MCT="8" Receive="0"/>
			<Cell CellID="AM_59" Value="0" MCT="10" Receive="0"/>
		</Cells>
		<Cells>
			<Cell CellID="D_60" FirstCell="1" Value="020102b" MCT="2"/>
			<Cell CellID="O_60" Value="M3" MCT="3"/>
			<Cell CellID="R_60" Value="0" MCT="4"/>
			<Cell CellID="U_60" Value="0" MCT="5"/>
			<Cell CellID="Z_60" Value="6.0000" MCT="6"/>
			<Cell CellID="AC_60" Value="0" MCT="7"/>
			<Cell CellID="AI_60" Value="0" MCT="9"/>
			<Cell CellID="AF_60" Value="0" MCT="8" Receive="0"/>
			<Cell CellID="AM_60" Value="0" MCT="10" Receive="0"/>
		</Cells>
		<Cells>
			<Cell CellID="D_61" FirstCell="1" Value="020103" MCT="2"/>
			<Cell CellID="O_61" Value="M3" MCT="3"/>
			<Cell CellID="R_61" Value="0" MCT="4"/>
			<Cell CellID="U_61" Value="0" MCT="5"/>
			<Cell CellID="Z_61" Value="7.0000" MCT="6"/>
			<Cell CellID="AC_61" Value="0" MCT="7"/>
			<Cell CellID="AI_61" Value="0" MCT="9"/>
			<Cell CellID="AF_61" Value="0" MCT="8" Receive="0"/>
			<Cell CellID="AM_61" Value="0" MCT="10" Receive="0"/>
		</Cells>
		<Cells>
			<Cell CellID="D_62" FirstCell="1" Value="020104" MCT="2"/>
			<Cell CellID="O_62" Value="M3" MCT="3"/>
			<Cell CellID="R_62" Value="0" MCT="4"/>
			<Cell CellID="U_62" Value="0" MCT="5"/>
			<Cell CellID="Z_62" Value="10.0000" MCT="6"/>
			<Cell CellID="AC_62" Value="0" MCT="7"/>
			<Cell CellID="AI_62" Value="0" MCT="9"/>
			<Cell CellID="AF_62" Value="0" MCT="8" Receive="0"/>
			<Cell CellID="AM_62" Value="0" MCT="10" Receive="0"/>
		</Cells>
		<Cells>
			<Cell CellID="D_63" FirstCell="1" Value="020105" MCT="2"/>
			<Cell CellID="O_63" Value="M3" MCT="3"/>
			<Cell CellID="R_63" Value="0" MCT="4"/>
			<Cell CellID="U_63" Value="0" MCT="5"/>
			<Cell CellID="Z_63" Value="11.0000" MCT="6"/>
			<Cell CellID="AC_63" Value="0" MCT="7"/>
			<Cell CellID="AI_63" Value="0" MCT="9"/>
			<Cell CellID="AF_63" Value="0" MCT="8" Receive="0"/>
			<Cell CellID="AM_63" Value="0" MCT="10" Receive="0"/>
		</Cells>
		<Cells>
			<Cell CellID="D_64" FirstCell="1" Value="020106" MCT="2"/>
			<Cell CellID="O_64" Value="M3" MCT="3"/>
			<Cell CellID="R_64" Value="0" MCT="4"/>
			<Cell CellID="U_64" Value="0" MCT="5"/>
			<Cell CellID="Z_64" Value="7.0000" MCT="6"/>
			<Cell CellID="AC_64" Value="0" MCT="7"/>
			<Cell CellID="AI_64" Value="0" MCT="9"/>
			<Cell CellID="AF_64" Value="0" MCT="8" Receive="0"/>
			<Cell CellID="AM_64" Value="0" MCT="10" Receive="0"/>
		</Cells>
		<Cells>
			<Cell CellID="D_65" FirstCell="1" Value="020201" MCT="2"/>
			<Cell CellID="O_65" Value="M3" MCT="3"/>
			<Cell CellID="R_65" Value="0" MCT="4"/>
			<Cell CellID="U_65" Value="0" MCT="5"/>
			<Cell CellID="Z_65" Value="7.0000" MCT="6"/>
			<Cell CellID="AC_65" Value="0" MCT="7"/>
			<Cell CellID="AI_65" Value="0" MCT="9"/>
			<Cell CellID="AF_65" Value="0" MCT="8" Receive="0"/>
			<Cell CellID="AM_65" Value="0" MCT="10" Receive="0"/>
		</Cells>
		<Cells>
			<Cell CellID="D_66" FirstCell="1" Value="020202" MCT="2"/>
			<Cell CellID="O_66" Value="M3" MCT="3"/>
			<Cell CellID="R_66" Value="0" MCT="4"/>
			<Cell CellID="U_66" Value="0" MCT="5"/>
			<Cell CellID="Z_66" Value="10.0000" MCT="6"/>
			<Cell CellID="AC_66" Value="0" MCT="7"/>
			<Cell CellID="AI_66" Value="0" MCT="9"/>
			<Cell CellID="AF_66" Value="0" MCT="8" Receive="0"/>
			<Cell CellID="AM_66" Value="0" MCT="10" Receive="0"/>
		</Cells>
		<Cells>
			<Cell CellID="D_67" FirstCell="1" Value="020203" MCT="2"/>
			<Cell CellID="O_67" Value="M3" MCT="3"/>
			<Cell CellID="R_67" Value="0" MCT="4"/>
			<Cell CellID="U_67" Value="0" MCT="5"/>
			<Cell CellID="Z_67" Value="10.0000" MCT="6"/>
			<Cell CellID="AC_67" Value="0" MCT="7"/>
			<Cell CellID="AI_67" Value="0" MCT="9"/>
			<Cell CellID="AF_67" Value="0" MCT="8" Receive="0"/>
			<Cell CellID="AM_67" Value="0" MCT="10" Receive="0"/>
		</Cells>
		<Cells>
			<Cell CellID="D_68" FirstCell="1" Value="020204" MCT="2"/>
			<Cell CellID="O_68" Value="M3" MCT="3"/>
			<Cell CellID="R_68" Value="0" MCT="4"/>
			<Cell CellID="U_68" Value="0" MCT="5"/>
			<Cell CellID="Z_68" Value="12.0000" MCT="6"/>
			<Cell CellID="AC_68" Value="0" MCT="7"/>
			<Cell CellID="AI_68" Value="0" MCT="9"/>
			<Cell CellID="AF_68" Value="0" MCT="8" Receive="0"/>
			<Cell CellID="AM_68" Value="0" MCT="10" Receive="0"/>
		</Cells>
		<Cells>
			<Cell CellID="D_69" FirstCell="1" Value="020301" MCT="2"/>
			<Cell CellID="O_69" Value="M3" MCT="3"/>
			<Cell CellID="R_69" Value="0" MCT="4"/>
			<Cell CellID="U_69" Value="0" MCT="5"/>
			<Cell CellID="Z_69" Value="7.0000" MCT="6"/>
			<Cell CellID="AC_69" Value="0" MCT="7"/>
			<Cell CellID="AI_69" Value="0" MCT="9"/>
			<Cell CellID="AF_69" Value="0" MCT="8" Receive="0"/>
			<Cell CellID="AM_69" Value="0" MCT="10" Receive="0"/>
		</Cells>
		<Cells>
			<Cell CellID="D_70" FirstCell="1" Value="020303" MCT="2"/>
			<Cell CellID="O_70" Value="M3" MCT="3"/>
			<Cell CellID="R_70" Value="0" MCT="4"/>
			<Cell CellID="U_70" Value="0" MCT="5"/>
			<Cell CellID="Z_70" Value="10.0000" MCT="6"/>
			<Cell CellID="AC_70" Value="0" MCT="7"/>
			<Cell CellID="AI_70" Value="0" MCT="9"/>
			<Cell CellID="AF_70" Value="0" MCT="8" Receive="0"/>
			<Cell CellID="AM_70" Value="0" MCT="10" Receive="0"/>
		</Cells>
		<Cells>
			<Cell CellID="D_71" FirstCell="1" Value="020304" MCT="2"/>
			<Cell CellID="O_71" Value="M3" MCT="3"/>
			<Cell CellID="R_71" Value="0" MCT="4"/>
			<Cell CellID="U_71" Value="0" MCT="5"/>
			<Cell CellID="Z_71" Value="10.0000" MCT="6"/>
			<Cell CellID="AC_71" Value="0" MCT="7"/>
			<Cell CellID="AI_71" Value="0" MCT="9"/>
			<Cell CellID="AF_71" Value="0" MCT="8" Receive="0"/>
			<Cell CellID="AM_71" Value="0" MCT="10" Receive="0"/>
		</Cells>
		<Cells>
			<Cell CellID="D_72" FirstCell="1" Value="020305" MCT="2"/>
			<Cell CellID="O_72" Value="M3" MCT="3"/>
			<Cell CellID="R_72" Value="0" MCT="4"/>
			<Cell CellID="U_72" Value="0" MCT="5"/>
			<Cell CellID="Z_72" Value="7.0000" MCT="6"/>
			<Cell CellID="AC_72" Value="0" MCT="7"/>
			<Cell CellID="AI_72" Value="0" MCT="9"/>
			<Cell CellID="AF_72" Value="0" MCT="8" Receive="0"/>
			<Cell CellID="AM_72" Value="0" MCT="10" Receive="0"/>
		</Cells>
		<Cells>
			<Cell CellID="D_73" FirstCell="1" Value="020302" MCT="2"/>
			<Cell CellID="O_73" Value="M3" MCT="3"/>
			<Cell CellID="R_73" Value="0" MCT="4"/>
			<Cell CellID="U_73" Value="0" MCT="5"/>
			<Cell CellID="Z_73" Value="3.0000" MCT="6"/>
			<Cell CellID="AC_73" Value="0" MCT="7"/>
			<Cell CellID="AI_73" Value="0" MCT="9"/>
			<Cell CellID="AF_73" Value="0" MCT="8" Receive="0"/>
			<Cell CellID="AM_73" Value="0" MCT="10" Receive="0"/>
		</Cells>
		<Cells>
			<Cell CellID="D_74" FirstCell="1" Value="0301a" MCT="2"/>
			<Cell CellID="O_74" Value="Tấn" MCT="3"/>
			<Cell CellID="R_74" Value="0" MCT="4"/>
			<Cell CellID="U_74" Value="0" MCT="5"/>
			<Cell CellID="Z_74" Value="4.0000" MCT="6"/>
			<Cell CellID="AC_74" Value="0" MCT="7"/>
			<Cell CellID="AI_74" Value="0" MCT="9"/>
			<Cell CellID="AF_74" Value="0" MCT="8" Receive="0"/>
			<Cell CellID="AM_74" Value="0" MCT="10" Receive="0"/>
		</Cells>
		<Cells>
			<Cell CellID="D_75" FirstCell="1" Value="0301b" MCT="2"/>
			<Cell CellID="O_75" Value="Tấn" MCT="3"/>
			<Cell CellID="R_75" Value="0" MCT="4"/>
			<Cell CellID="U_75" Value="0" MCT="5"/>
			<Cell CellID="Z_75" Value="5.0000" MCT="6"/>
			<Cell CellID="AC_75" Value="0" MCT="7"/>
			<Cell CellID="AI_75" Value="0" MCT="9"/>
			<Cell CellID="AF_75" Value="0" MCT="8" Receive="0"/>
			<Cell CellID="AM_75" Value="0" MCT="10" Receive="0"/>
		</Cells>
		<Cells>
			<Cell CellID="D_76" FirstCell="1" Value="0302a" MCT="2"/>
			<Cell CellID="O_76" Value="Tấn" MCT="3"/>
			<Cell CellID="R_76" Value="0" MCT="4"/>
			<Cell CellID="U_76" Value="0" MCT="5"/>
			<Cell CellID="Z_76" Value="6.0000" MCT="6"/>
			<Cell CellID="AC_76" Value="0" MCT="7"/>
			<Cell CellID="AI_76" Value="0" MCT="9"/>
			<Cell CellID="AF_76" Value="0" MCT="8" Receive="0"/>
			<Cell CellID="AM_76" Value="0" MCT="10" Receive="0"/>
		</Cells>
		<Cells>
			<Cell CellID="D_77" FirstCell="1" Value="0302b" MCT="2"/>
			<Cell CellID="O_77" Value="Tấn" MCT="3"/>
			<Cell CellID="R_77" Value="0" MCT="4"/>
			<Cell CellID="U_77" Value="0" MCT="5"/>
			<Cell CellID="Z_77" Value="7.0000" MCT="6"/>
			<Cell CellID="AC_77" Value="0" MCT="7"/>
			<Cell CellID="AI_77" Value="0" MCT="9"/>
			<Cell CellID="AF_77" Value="0" MCT="8" Receive="0"/>
			<Cell CellID="AM_77" Value="0" MCT="10" Receive="0"/>
		</Cells>
		<Cells>
			<Cell CellID="D_78" FirstCell="1" Value="0303a" MCT="2"/>
			<Cell CellID="O_78" Value="Tấn" MCT="3"/>
			<Cell CellID="R_78" Value="0" MCT="4"/>
			<Cell CellID="U_78" Value="0" MCT="5"/>
			<Cell CellID="Z_78" Value="6.0000" MCT="6"/>
			<Cell CellID="AC_78" Value="0" MCT="7"/>
			<Cell CellID="AI_78" Value="0" MCT="9"/>
			<Cell CellID="AF_78" Value="0" MCT="8" Receive="0"/>
			<Cell CellID="AM_78" Value="0" MCT="10" Receive="0"/>
		</Cells>
		<Cells>
			<Cell CellID="D_79" FirstCell="1" Value="0303b" MCT="2"/>
			<Cell CellID="O_79" Value="Tấn" MCT="3"/>
			<Cell CellID="R_79" Value="0" MCT="4"/>
			<Cell CellID="U_79" Value="0" MCT="5"/>
			<Cell CellID="Z_79" Value="7.0000" MCT="6"/>
			<Cell CellID="AC_79" Value="0" MCT="7"/>
			<Cell CellID="AI_79" Value="0" MCT="9"/>
			<Cell CellID="AF_79" Value="0" MCT="8" Receive="0"/>
			<Cell CellID="AM_79" Value="0" MCT="10" Receive="0"/>
		</Cells>
		<Cells>
			<Cell CellID="D_80" FirstCell="1" Value="0304a" MCT="2"/>
			<Cell CellID="O_80" Value="Tấn" MCT="3"/>
			<Cell CellID="R_80" Value="0" MCT="4"/>
			<Cell CellID="U_80" Value="0" MCT="5"/>
			<Cell CellID="Z_80" Value="4.0000" MCT="6"/>
			<Cell CellID="AC_80" Value="0" MCT="7"/>
			<Cell CellID="AI_80" Value="0" MCT="9"/>
			<Cell CellID="AF_80" Value="0" MCT="8" Receive="0"/>
			<Cell CellID="AM_80" Value="0" MCT="10" Receive="0"/>
		</Cells>
		<Cells>
			<Cell CellID="D_81" FirstCell="1" Value="0304b" MCT="2"/>
			<Cell CellID="O_81" Value="Tấn" MCT="3"/>
			<Cell CellID="R_81" Value="0" MCT="4"/>
			<Cell CellID="U_81" Value="0" MCT="5"/>
			<Cell CellID="Z_81" Value="5.0000" MCT="6"/>
			<Cell CellID="AC_81" Value="0" MCT="7"/>
			<Cell CellID="AI_81" Value="0" MCT="9"/>
			<Cell CellID="AF_81" Value="0" MCT="8" Receive="0"/>
			<Cell CellID="AM_81" Value="0" MCT="10" Receive="0"/>
		</Cells>
		<Cells>
			<Cell CellID="D_82" FirstCell="1" Value="0401a" MCT="2"/>
			<Cell CellID="O_82" Value="M3" MCT="3"/>
			<Cell CellID="R_82" Value="0" MCT="4"/>
			<Cell CellID="U_82" Value="0" MCT="5"/>
			<Cell CellID="Z_82" Value="16.0000" MCT="6"/>
			<Cell CellID="AC_82" Value="0" MCT="7"/>
			<Cell CellID="AI_82" Value="0" MCT="9"/>
			<Cell CellID="AF_82" Value="0" MCT="8" Receive="0"/>
			<Cell CellID="AM_82" Value="0" MCT="10" Receive="0"/>
		</Cells>
		<Cells>
			<Cell CellID="D_83" FirstCell="1" Value="0401b" MCT="2"/>
			<Cell CellID="O_83" Value="M3" MCT="3"/>
			<Cell CellID="R_83" Value="0" MCT="4"/>
			<Cell CellID="U_83" Value="0" MCT="5"/>
			<Cell CellID="Z_83" Value="22.0000" MCT="6"/>
			<Cell CellID="AC_83" Value="0" MCT="7"/>
			<Cell CellID="AI_83" Value="0" MCT="9"/>
			<Cell CellID="AF_83" Value="0" MCT="8" Receive="0"/>
			<Cell CellID="AM_83" Value="0" MCT="10" Receive="0"/>
		</Cells>
		<Cells>
			<Cell CellID="D_84" FirstCell="1" Value="0405" MCT="2"/>
			<Cell CellID="O_84" Value="M3" MCT="3"/>
			<Cell CellID="R_84" Value="0" MCT="4"/>
			<Cell CellID="U_84" Value="0" MCT="5"/>
			<Cell CellID="Z_84" Value="20.0000" MCT="6"/>
			<Cell CellID="AC_84" Value="0" MCT="7"/>
			<Cell CellID="AI_84" Value="0" MCT="9"/>
			<Cell CellID="AF_84" Value="0" MCT="8" Receive="0"/>
			<Cell CellID="AM_84" Value="0" MCT="10" Receive="0"/>
		</Cells>
		<Cells>
			<Cell CellID="D_85" FirstCell="1" Value="0402" MCT="2"/>
			<Cell CellID="O_85" Value="M3" MCT="3"/>
			<Cell CellID="R_85" Value="0" MCT="4"/>
			<Cell CellID="U_85" Value="0" MCT="5"/>
			<Cell CellID="Z_85" Value="12.0000" MCT="6"/>
			<Cell CellID="AC_85" Value="0" MCT="7"/>
			<Cell CellID="AI_85" Value="0" MCT="9"/>
			<Cell CellID="AF_85" Value="0" MCT="8" Receive="0"/>
			<Cell CellID="AM_85" Value="0" MCT="10" Receive="0"/>
		</Cells>
		<Cells>
			<Cell CellID="D_86" FirstCell="1" Value="0406" MCT="2"/>
			<Cell CellID="O_86" Value="M3" MCT="3"/>
			<Cell CellID="R_86" Value="0" MCT="4"/>
			<Cell CellID="U_86" Value="0" MCT="5"/>
			<Cell CellID="Z_86" Value="15.0000" MCT="6"/>
			<Cell CellID="AC_86" Value="0" MCT="7"/>
			<Cell CellID="AI_86" Value="0" MCT="9"/>
			<Cell CellID="AF_86" Value="0" MCT="8" Receive="0"/>
			<Cell CellID="AM_86" Value="0" MCT="10" Receive="0"/>
		</Cells>
		<Cells>
			<Cell CellID="D_87" FirstCell="1" Value="0403" MCT="2"/>
			<Cell CellID="O_87" Value="M3" MCT="3"/>
			<Cell CellID="R_87" Value="0" MCT="4"/>
			<Cell CellID="U_87" Value="0" MCT="5"/>
			<Cell CellID="Z_87" Value="10.0000" MCT="6"/>
			<Cell CellID="AC_87" Value="0" MCT="7"/>
			<Cell CellID="AI_87" Value="0" MCT="9"/>
			<Cell CellID="AF_87" Value="0" MCT="8" Receive="0"/>
			<Cell CellID="AM_87" Value="0" MCT="10" Receive="0"/>
		</Cells>
		<Cells>
			<Cell CellID="D_88" FirstCell="1" Value="0407" MCT="2"/>
			<Cell CellID="O_88" Value="M3" MCT="3"/>
			<Cell CellID="R_88" Value="0" MCT="4"/>
			<Cell CellID="U_88" Value="0" MCT="5"/>
			<Cell CellID="Z_88" Value="15.0000" MCT="6"/>
			<Cell CellID="AC_88" Value="0" MCT="7"/>
			<Cell CellID="AI_88" Value="0" MCT="9"/>
			<Cell CellID="AF_88" Value="0" MCT="8" Receive="0"/>
			<Cell CellID="AM_88" Value="0" MCT="10" Receive="0"/>
		</Cells>
		<Cells>
			<Cell CellID="D_89" FirstCell="1" Value="0404a" MCT="2"/>
			<Cell CellID="O_89" Value="M3" MCT="3"/>
			<Cell CellID="R_89" Value="0" MCT="4"/>
			<Cell CellID="U_89" Value="0" MCT="5"/>
			<Cell CellID="Z_89" Value="4.0000" MCT="6"/>
			<Cell CellID="AC_89" Value="0" MCT="7"/>
			<Cell CellID="AI_89" Value="0" MCT="9"/>
			<Cell CellID="AF_89" Value="0" MCT="8" Receive="0"/>
			<Cell CellID="AM_89" Value="0" MCT="10" Receive="0"/>
		</Cells>
		<Cells>
			<Cell CellID="D_90" FirstCell="1" Value="0404b" MCT="2"/>
			<Cell CellID="O_90" Value="M3" MCT="3"/>
			<Cell CellID="R_90" Value="0" MCT="4"/>
			<Cell CellID="U_90" Value="0" MCT="5"/>
			<Cell CellID="Z_90" Value="5.0000" MCT="6"/>
			<Cell CellID="AC_90" Value="0" MCT="7"/>
			<Cell CellID="AI_90" Value="0" MCT="9"/>
			<Cell CellID="AF_90" Value="0" MCT="8" Receive="0"/>
			<Cell CellID="AM_90" Value="0" MCT="10" Receive="0"/>
		</Cells>
		<Cells>
			<Cell CellID="D_91" FirstCell="1" Value="050101a" MCT="2"/>
			<Cell CellID="O_91" Value="Tấn" MCT="3"/>
			<Cell CellID="R_91" Value="0" MCT="4"/>
			<Cell CellID="U_91" Value="0" MCT="5"/>
			<Cell CellID="Z_91" Value="6.0000" MCT="6"/>
			<Cell CellID="AC_91" Value="0" MCT="7"/>
			<Cell CellID="AI_91" Value="0" MCT="9"/>
			<Cell CellID="AF_91" Value="0" MCT="8" Receive="0"/>
			<Cell CellID="AM_91" Value="0" MCT="10" Receive="0"/>
		</Cells>
		<Cells>
			<Cell CellID="D_92" FirstCell="1" Value="050101b" MCT="2"/>
			<Cell CellID="O_92" Value="Tấn" MCT="3"/>
			<Cell CellID="R_92" Value="0" MCT="4"/>
			<Cell CellID="U_92" Value="0" MCT="5"/>
			<Cell CellID="Z_92" Value="7.0000" MCT="6"/>
			<Cell CellID="AC_92" Value="0" MCT="7"/>
			<Cell CellID="AI_92" Value="0" MCT="9"/>
			<Cell CellID="AF_92" Value="0" MCT="8" Receive="0"/>
			<Cell CellID="AM_92" Value="0" MCT="10" Receive="0"/>
		</Cells>
		<Cells>
			<Cell CellID="D_93" FirstCell="1" Value="050102a" MCT="2"/>
			<Cell CellID="O_93" Value="Tấn" MCT="3"/>
			<Cell CellID="R_93" Value="0" MCT="4"/>
			<Cell CellID="U_93" Value="0" MCT="5"/>
			<Cell CellID="Z_93" Value="8.0000" MCT="6"/>
			<Cell CellID="AC_93" Value="0" MCT="7"/>
			<Cell CellID="AI_93" Value="0" MCT="9"/>
			<Cell CellID="AF_93" Value="0" MCT="8" Receive="0"/>
			<Cell CellID="AM_93" Value="0" MCT="10" Receive="0"/>
		</Cells>
		<Cells>
			<Cell CellID="D_94" FirstCell="1" Value="050102b" MCT="2"/>
			<Cell CellID="O_94" Value="Tấn" MCT="3"/>
			<Cell CellID="R_94" Value="0" MCT="4"/>
			<Cell CellID="U_94" Value="0" MCT="5"/>
			<Cell CellID="Z_94" Value="9.0000" MCT="6"/>
			<Cell CellID="AC_94" Value="0" MCT="7"/>
			<Cell CellID="AI_94" Value="0" MCT="9"/>
			<Cell CellID="AF_94" Value="0" MCT="8" Receive="0"/>
			<Cell CellID="AM_94" Value="0" MCT="10" Receive="0"/>
		</Cells>
		<Cells>
			<Cell CellID="D_95" FirstCell="1" Value="050103a" MCT="2"/>
			<Cell CellID="O_95" Value="Tấn" MCT="3"/>
			<Cell CellID="R_95" Value="0" MCT="4"/>
			<Cell CellID="U_95" Value="0" MCT="5"/>
			<Cell CellID="Z_95" Value="10.0000" MCT="6"/>
			<Cell CellID="AC_95" Value="0" MCT="7"/>
			<Cell CellID="AI_95" Value="0" MCT="9"/>
			<Cell CellID="AF_95" Value="0" MCT="8" Receive="0"/>
			<Cell CellID="AM_95" Value="0" MCT="10" Receive="0"/>
		</Cells>
		<Cells>
			<Cell CellID="D_96" FirstCell="1" Value="050103b" MCT="2"/>
			<Cell CellID="O_96" Value="Tấn" MCT="3"/>
			<Cell CellID="R_96" Value="0" MCT="4"/>
			<Cell CellID="U_96" Value="0" MCT="5"/>
			<Cell CellID="Z_96" Value="11.0000" MCT="6"/>
			<Cell CellID="AC_96" Value="0" MCT="7"/>
			<Cell CellID="AI_96" Value="0" MCT="9"/>
			<Cell CellID="AF_96" Value="0" MCT="8" Receive="0"/>
			<Cell CellID="AM_96" Value="0" MCT="10" Receive="0"/>
		</Cells>
		<Cells>
			<Cell CellID="D_97" FirstCell="1" Value="050104a" MCT="2"/>
			<Cell CellID="O_97" Value="Tấn" MCT="3"/>
			<Cell CellID="R_97" Value="0" MCT="4"/>
			<Cell CellID="U_97" Value="0" MCT="5"/>
			<Cell CellID="Z_97" Value="12.0000" MCT="6"/>
			<Cell CellID="AC_97" Value="0" MCT="7"/>
			<Cell CellID="AI_97" Value="0" MCT="9"/>
			<Cell CellID="AF_97" Value="0" MCT="8" Receive="0"/>
			<Cell CellID="AM_97" Value="0" MCT="10" Receive="0"/>
		</Cells>
		<Cells>
			<Cell CellID="D_98" FirstCell="1" Value="050104b" MCT="2"/>
			<Cell CellID="O_98" Value="Tấn" MCT="3"/>
			<Cell CellID="R_98" Value="0" MCT="4"/>
			<Cell CellID="U_98" Value="0" MCT="5"/>
			<Cell CellID="Z_98" Value="13.0000" MCT="6"/>
			<Cell CellID="AC_98" Value="0" MCT="7"/>
			<Cell CellID="AI_98" Value="0" MCT="9"/>
			<Cell CellID="AF_98" Value="0" MCT="8" Receive="0"/>
			<Cell CellID="AM_98" Value="0" MCT="10" Receive="0"/>
		</Cells>
		<Cells>
			<Cell CellID="D_99" FirstCell="1" Value="050105a" MCT="2"/>
			<Cell CellID="O_99" Value="Tấn" MCT="3"/>
			<Cell CellID="R_99" Value="0" MCT="4"/>
			<Cell CellID="U_99" Value="0" MCT="5"/>
			<Cell CellID="Z_99" Value="17.0000" MCT="6"/>
			<Cell CellID="AC_99" Value="0" MCT="7"/>
			<Cell CellID="AI_99" Value="0" MCT="9"/>
			<Cell CellID="AF_99" Value="0" MCT="8" Receive="0"/>
			<Cell CellID="AM_99" Value="0" MCT="10" Receive="0"/>
		</Cells>
		<Cells>
			<Cell CellID="D_100" FirstCell="1" Value="050105b" MCT="2"/>
			<Cell CellID="O_100" Value="Tấn" MCT="3"/>
			<Cell CellID="R_100" Value="0" MCT="4"/>
			<Cell CellID="U_100" Value="0" MCT="5"/>
			<Cell CellID="Z_100" Value="18.0000" MCT="6"/>
			<Cell CellID="AC_100" Value="0" MCT="7"/>
			<Cell CellID="AI_100" Value="0" MCT="9"/>
			<Cell CellID="AF_100" Value="0" MCT="8" Receive="0"/>
			<Cell CellID="AM_100" Value="0" MCT="10" Receive="0"/>
		</Cells>
		<Cells>
			<Cell CellID="D_101" FirstCell="1" Value="050106a" MCT="2"/>
			<Cell CellID="O_101" Value="Tấn" MCT="3"/>
			<Cell CellID="R_101" Value="0" MCT="4"/>
			<Cell CellID="U_101" Value="0" MCT="5"/>
			<Cell CellID="Z_101" Value="22.0000" MCT="6"/>
			<Cell CellID="AC_101" Value="0" MCT="7"/>
			<Cell CellID="AI_101" Value="0" MCT="9"/>
			<Cell CellID="AF_101" Value="0" MCT="8" Receive="0"/>
			<Cell CellID="AM_101" Value="0" MCT="10" Receive="0"/>
		</Cells>
		<Cells>
			<Cell CellID="D_102" FirstCell="1" Value="050106b" MCT="2"/>
			<Cell CellID="O_102" Value="Tấn" MCT="3"/>
			<Cell CellID="R_102" Value="0" MCT="4"/>
			<Cell CellID="U_102" Value="0" MCT="5"/>
			<Cell CellID="Z_102" Value="23.0000" MCT="6"/>
			<Cell CellID="AC_102" Value="0" MCT="7"/>
			<Cell CellID="AI_102" Value="0" MCT="9"/>
			<Cell CellID="AF_102" Value="0" MCT="8" Receive="0"/>
			<Cell CellID="AM_102" Value="0" MCT="10" Receive="0"/>
		</Cells>
		<Cells>
			<Cell CellID="D_103" FirstCell="1" Value="050201a" MCT="2"/>
			<Cell CellID="O_103" Value="Tấn" MCT="3"/>
			<Cell CellID="R_103" Value="0" MCT="4"/>
			<Cell CellID="U_103" Value="0" MCT="5"/>
			<Cell CellID="Z_103" Value="8.0000" MCT="6"/>
			<Cell CellID="AC_103" Value="0" MCT="7"/>
			<Cell CellID="AI_103" Value="0" MCT="9"/>
			<Cell CellID="AF_103" Value="0" MCT="8" Receive="0"/>
			<Cell CellID="AM_103" Value="0" MCT="10" Receive="0"/>
		</Cells>
		<Cells>
			<Cell CellID="D_104" FirstCell="1" Value="050201b" MCT="2"/>
			<Cell CellID="O_104" Value="Tấn" MCT="3"/>
			<Cell CellID="R_104" Value="0" MCT="4"/>
			<Cell CellID="U_104" Value="0" MCT="5"/>
			<Cell CellID="Z_104" Value="10.0000" MCT="6"/>
			<Cell CellID="AC_104" Value="0" MCT="7"/>
			<Cell CellID="AI_104" Value="0" MCT="9"/>
			<Cell CellID="AF_104" Value="0" MCT="8" Receive="0"/>
			<Cell CellID="AM_104" Value="0" MCT="10" Receive="0"/>
		</Cells>
		<Cells>
			<Cell CellID="D_105" FirstCell="1" Value="050202a" MCT="2"/>
			<Cell CellID="O_105" Value="Tấn" MCT="3"/>
			<Cell CellID="R_105" Value="0" MCT="4"/>
			<Cell CellID="U_105" Value="0" MCT="5"/>
			<Cell CellID="Z_105" Value="10.0000" MCT="6"/>
			<Cell CellID="AC_105" Value="0" MCT="7"/>
			<Cell CellID="AI_105" Value="0" MCT="9"/>
			<Cell CellID="AF_105" Value="0" MCT="8" Receive="0"/>
			<Cell CellID="AM_105" Value="0" MCT="10" Receive="0"/>
		</Cells>
		<Cells>
			<Cell CellID="D_106" FirstCell="1" Value="050202b" MCT="2"/>
			<Cell CellID="O_106" Value="Tấn" MCT="3"/>
			<Cell CellID="R_106" Value="0" MCT="4"/>
			<Cell CellID="U_106" Value="0" MCT="5"/>
			<Cell CellID="Z_106" Value="12.0000" MCT="6"/>
			<Cell CellID="AC_106" Value="0" MCT="7"/>
			<Cell CellID="AI_106" Value="0" MCT="9"/>
			<Cell CellID="AF_106" Value="0" MCT="8" Receive="0"/>
			<Cell CellID="AM_106" Value="0" MCT="10" Receive="0"/>
		</Cells>
		<Cells>
			<Cell CellID="D_107" FirstCell="1" Value="050203a" MCT="2"/>
			<Cell CellID="O_107" Value="Tấn" MCT="3"/>
			<Cell CellID="R_107" Value="0" MCT="4"/>
			<Cell CellID="U_107" Value="0" MCT="5"/>
			<Cell CellID="Z_107" Value="12.0000" MCT="6"/>
			<Cell CellID="AC_107" Value="0" MCT="7"/>
			<Cell CellID="AI_107" Value="0" MCT="9"/>
			<Cell CellID="AF_107" Value="0" MCT="8" Receive="0"/>
			<Cell CellID="AM_107" Value="0" MCT="10" Receive="0"/>
		</Cells>
		<Cells>
			<Cell CellID="D_108" FirstCell="1" Value="050203b" MCT="2"/>
			<Cell CellID="O_108" Value="Tấn" MCT="3"/>
			<Cell CellID="R_108" Value="0" MCT="4"/>
			<Cell CellID="U_108" Value="0" MCT="5"/>
			<Cell CellID="Z_108" Value="14.0000" MCT="6"/>
			<Cell CellID="AC_108" Value="0" MCT="7"/>
			<Cell CellID="AI_108" Value="0" MCT="9"/>
			<Cell CellID="AF_108" Value="0" MCT="8" Receive="0"/>
			<Cell CellID="AM_108" Value="0" MCT="10" Receive="0"/>
		</Cells>
		<Cells>
			<Cell CellID="D_109" FirstCell="1" Value="050204a" MCT="2"/>
			<Cell CellID="O_109" Value="Tấn" MCT="3"/>
			<Cell CellID="R_109" Value="0" MCT="4"/>
			<Cell CellID="U_109" Value="0" MCT="5"/>
			<Cell CellID="Z_109" Value="17.0000" MCT="6"/>
			<Cell CellID="AC_109" Value="0" MCT="7"/>
			<Cell CellID="AI_109" Value="0" MCT="9"/>
			<Cell CellID="AF_109" Value="0" MCT="8" Receive="0"/>
			<Cell CellID="AM_109" Value="0" MCT="10" Receive="0"/>
		</Cells>
		<Cells>
			<Cell CellID="D_110" FirstCell="1" Value="050204b" MCT="2"/>
			<Cell CellID="O_110" Value="Tấn" MCT="3"/>
			<Cell CellID="R_110" Value="0" MCT="4"/>
			<Cell CellID="U_110" Value="0" MCT="5"/>
			<Cell CellID="Z_110" Value="19.0000" MCT="6"/>
			<Cell CellID="AC_110" Value="0" MCT="7"/>
			<Cell CellID="AI_110" Value="0" MCT="9"/>
			<Cell CellID="AF_110" Value="0" MCT="8" Receive="0"/>
			<Cell CellID="AM_110" Value="0" MCT="10" Receive="0"/>
		</Cells>
		<Cells>
			<Cell CellID="D_111" FirstCell="1" Value="050205a" MCT="2"/>
			<Cell CellID="O_111" Value="Tấn" MCT="3"/>
			<Cell CellID="R_111" Value="0" MCT="4"/>
			<Cell CellID="U_111" Value="0" MCT="5"/>
			<Cell CellID="Z_111" Value="22.0000" MCT="6"/>
			<Cell CellID="AC_111" Value="0" MCT="7"/>
			<Cell CellID="AI_111" Value="0" MCT="9"/>
			<Cell CellID="AF_111" Value="0" MCT="8" Receive="0"/>
			<Cell CellID="AM_111" Value="0" MCT="10" Receive="0"/>
		</Cells>
		<Cells>
			<Cell CellID="D_112" FirstCell="1" Value="050205b" MCT="2"/>
			<Cell CellID="O_112" Value="Tấn" MCT="3"/>
			<Cell CellID="R_112" Value="0" MCT="4"/>
			<Cell CellID="U_112" Value="0" MCT="5"/>
			<Cell CellID="Z_112" Value="24.0000" MCT="6"/>
			<Cell CellID="AC_112" Value="0" MCT="7"/>
			<Cell CellID="AI_112" Value="0" MCT="9"/>
			<Cell CellID="AF_112" Value="0" MCT="8" Receive="0"/>
			<Cell CellID="AM_112" Value="0" MCT="10" Receive="0"/>
		</Cells>
		<Cells>
			<Cell CellID="D_113" FirstCell="1" Value="050206a" MCT="2"/>
			<Cell CellID="O_113" Value="Tấn" MCT="3"/>
			<Cell CellID="R_113" Value="0" MCT="4"/>
			<Cell CellID="U_113" Value="0" MCT="5"/>
			<Cell CellID="Z_113" Value="27.0000" MCT="6"/>
			<Cell CellID="AC_113" Value="0" MCT="7"/>
			<Cell CellID="AI_113" Value="0" MCT="9"/>
			<Cell CellID="AF_113" Value="0" MCT="8" Receive="0"/>
			<Cell CellID="AM_113" Value="0" MCT="10" Receive="0"/>
		</Cells>
		<Cells>
			<Cell CellID="D_114" FirstCell="1" Value="050206b" MCT="2"/>
			<Cell CellID="O_114" Value="Tấn" MCT="3"/>
			<Cell CellID="R_114" Value="0" MCT="4"/>
			<Cell CellID="U_114" Value="0" MCT="5"/>
			<Cell CellID="Z_114" Value="29.0000" MCT="6"/>
			<Cell CellID="AC_114" Value="0" MCT="7"/>
			<Cell CellID="AI_114" Value="0" MCT="9"/>
			<Cell CellID="AF_114" Value="0" MCT="8" Receive="0"/>
			<Cell CellID="AM_114" Value="0" MCT="10" Receive="0"/>
		</Cells>
		<Cells>
			<Cell CellID="D_115" FirstCell="1" Value="060101a" MCT="2"/>
			<Cell CellID="O_115" Value="M3" MCT="3"/>
			<Cell CellID="R_115" Value="0" MCT="4"/>
			<Cell CellID="U_115" Value="0" MCT="5"/>
			<Cell CellID="Z_115" Value="0.0000" MCT="6"/>
			<Cell CellID="AC_115" Value="0" MCT="7"/>
			<Cell CellID="AI_115" Value="0" MCT="9"/>
			<Cell CellID="AF_115" Value="0" MCT="8" Receive="0"/>
			<Cell CellID="AM_115" Value="0" MCT="10" Receive="0"/>
		</Cells>
		<Cells>
			<Cell CellID="D_116" FirstCell="1" Value="060101b" MCT="2"/>
			<Cell CellID="O_116" Value="M3" MCT="3"/>
			<Cell CellID="R_116" Value="0" MCT="4"/>
			<Cell CellID="U_116" Value="0" MCT="5"/>
			<Cell CellID="Z_116" Value="1.0000" MCT="6"/>
			<Cell CellID="AC_116" Value="0" MCT="7"/>
			<Cell CellID="AI_116" Value="0" MCT="9"/>
			<Cell CellID="AF_116" Value="0" MCT="8" Receive="0"/>
			<Cell CellID="AM_116" Value="0" MCT="10" Receive="0"/>
		</Cells>
		<Cells>
			<Cell CellID="D_117" FirstCell="1" Value="060102a" MCT="2"/>
			<Cell CellID="O_117" Value="M3" MCT="3"/>
			<Cell CellID="R_117" Value="0" MCT="4"/>
			<Cell CellID="U_117" Value="0" MCT="5"/>
			<Cell CellID="Z_117" Value="3.0000" MCT="6"/>
			<Cell CellID="AC_117" Value="0" MCT="7"/>
			<Cell CellID="AI_117" Value="0" MCT="9"/>
			<Cell CellID="AF_117" Value="0" MCT="8" Receive="0"/>
			<Cell CellID="AM_117" Value="0" MCT="10" Receive="0"/>
		</Cells>
		<Cells>
			<Cell CellID="D_118" FirstCell="1" Value="060102b" MCT="2"/>
			<Cell CellID="O_118" Value="M3" MCT="3"/>
			<Cell CellID="R_118" Value="0" MCT="4"/>
			<Cell CellID="U_118" Value="0" MCT="5"/>
			<Cell CellID="Z_118" Value="3.0000" MCT="6"/>
			<Cell CellID="AC_118" Value="0" MCT="7"/>
			<Cell CellID="AI_118" Value="0" MCT="9"/>
			<Cell CellID="AF_118" Value="0" MCT="8" Receive="0"/>
			<Cell CellID="AM_118" Value="0" MCT="10" Receive="0"/>
		</Cells>
		<Cells>
			<Cell CellID="D_119" FirstCell="1" Value="060103" MCT="2"/>
			<Cell CellID="O_119" Value="M3" MCT="3"/>
			<Cell CellID="R_119" Value="0" MCT="4"/>
			<Cell CellID="U_119" Value="0" MCT="5"/>
			<Cell CellID="Z_119" Value="6.0000" MCT="6"/>
			<Cell CellID="AC_119" Value="0" MCT="7"/>
			<Cell CellID="AI_119" Value="0" MCT="9"/>
			<Cell CellID="AF_119" Value="0" MCT="8" Receive="0"/>
			<Cell CellID="AM_119" Value="0" MCT="10" Receive="0"/>
		</Cells>
		<Cells>
			<Cell CellID="D_120" FirstCell="1" Value="060201a" MCT="2"/>
			<Cell CellID="O_120" Value="M3" MCT="3"/>
			<Cell CellID="R_120" Value="0" MCT="4"/>
			<Cell CellID="U_120" Value="0" MCT="5"/>
			<Cell CellID="Z_120" Value="0.0000" MCT="6"/>
			<Cell CellID="AC_120" Value="0" MCT="7"/>
			<Cell CellID="AI_120" Value="0" MCT="9"/>
			<Cell CellID="AF_120" Value="0" MCT="8" Receive="0"/>
			<Cell CellID="AM_120" Value="0" MCT="10" Receive="0"/>
		</Cells>
		<Cells>
			<Cell CellID="D_121" FirstCell="1" Value="060201b" MCT="2"/>
			<Cell CellID="O_121" Value="M3" MCT="3"/>
			<Cell CellID="R_121" Value="0" MCT="4"/>
			<Cell CellID="U_121" Value="0" MCT="5"/>
			<Cell CellID="Z_121" Value="2.0000" MCT="6"/>
			<Cell CellID="AC_121" Value="0" MCT="7"/>
			<Cell CellID="AI_121" Value="0" MCT="9"/>
			<Cell CellID="AF_121" Value="0" MCT="8" Receive="0"/>
			<Cell CellID="AM_121" Value="0" MCT="10" Receive="0"/>
		</Cells>
		<Cells>
			<Cell CellID="D_122" FirstCell="1" Value="060202a" MCT="2"/>
			<Cell CellID="O_122" Value="M3" MCT="3"/>
			<Cell CellID="R_122" Value="0" MCT="4"/>
			<Cell CellID="U_122" Value="0" MCT="5"/>
			<Cell CellID="Z_122" Value="5.0000" MCT="6"/>
			<Cell CellID="AC_122" Value="0" MCT="7"/>
			<Cell CellID="AI_122" Value="0" MCT="9"/>
			<Cell CellID="AF_122" Value="0" MCT="8" Receive="0"/>
			<Cell CellID="AM_122" Value="0" MCT="10" Receive="0"/>
		</Cells>
		<Cells>
			<Cell CellID="D_123" FirstCell="1" Value="060202b" MCT="2"/>
			<Cell CellID="O_123" Value="M3" MCT="3"/>
			<Cell CellID="R_123" Value="0" MCT="4"/>
			<Cell CellID="U_123" Value="0" MCT="5"/>
			<Cell CellID="Z_123" Value="5.0000" MCT="6"/>
			<Cell CellID="AC_123" Value="0" MCT="7"/>
			<Cell CellID="AI_123" Value="0" MCT="9"/>
			<Cell CellID="AF_123" Value="0" MCT="8" Receive="0"/>
			<Cell CellID="AM_123" Value="0" MCT="10" Receive="0"/>
		</Cells>
		<Cells>
			<Cell CellID="D_124" FirstCell="1" Value="060203a" MCT="2"/>
			<Cell CellID="O_124" Value="M3" MCT="3"/>
			<Cell CellID="R_124" Value="0" MCT="4"/>
			<Cell CellID="U_124" Value="0" MCT="5"/>
			<Cell CellID="Z_124" Value="10.0000" MCT="6"/>
			<Cell CellID="AC_124" Value="0" MCT="7"/>
			<Cell CellID="AI_124" Value="0" MCT="9"/>
			<Cell CellID="AF_124" Value="0" MCT="8" Receive="0"/>
			<Cell CellID="AM_124" Value="0" MCT="10" Receive="0"/>
		</Cells>
		<Cells>
			<Cell CellID="D_125" FirstCell="1" Value="060203b" MCT="2"/>
			<Cell CellID="O_125" Value="M3" MCT="3"/>
			<Cell CellID="R_125" Value="0" MCT="4"/>
			<Cell CellID="U_125" Value="0" MCT="5"/>
			<Cell CellID="Z_125" Value="10.0000" MCT="6"/>
			<Cell CellID="AC_125" Value="0" MCT="7"/>
			<Cell CellID="AI_125" Value="0" MCT="9"/>
			<Cell CellID="AF_125" Value="0" MCT="8" Receive="0"/>
			<Cell CellID="AM_125" Value="0" MCT="10" Receive="0"/>
		</Cells>
		<Cells>
			<Cell CellID="D_126" FirstCell="1" Value="070101a" MCT="2"/>
			<Cell CellID="O_126" Value="M3" MCT="3"/>
			<Cell CellID="R_126" Value="0" MCT="4"/>
			<Cell CellID="U_126" Value="0" MCT="5"/>
			<Cell CellID="Z_126" Value="40.0000" MCT="6"/>
			<Cell CellID="AC_126" Value="0" MCT="7"/>
			<Cell CellID="AI_126" Value="0" MCT="9"/>
			<Cell CellID="AF_126" Value="0" MCT="8" Receive="0"/>
			<Cell CellID="AM_126" Value="0" MCT="10" Receive="0"/>
		</Cells>
		<Cells>
			<Cell CellID="D_127" FirstCell="1" Value="070101b" MCT="2"/>
			<Cell CellID="O_127" Value="M3" MCT="3"/>
			<Cell CellID="R_127" Value="0" MCT="4"/>
			<Cell CellID="U_127" Value="0" MCT="5"/>
			<Cell CellID="Z_127" Value="35.0000" MCT="6"/>
			<Cell CellID="AC_127" Value="0" MCT="7"/>
			<Cell CellID="AI_127" Value="0" MCT="9"/>
			<Cell CellID="AF_127" Value="0" MCT="8" Receive="0"/>
			<Cell CellID="AM_127" Value="0" MCT="10" Receive="0"/>
		</Cells>
		<Cells>
			<Cell CellID="D_128" FirstCell="1" Value="070102a" MCT="2"/>
			<Cell CellID="O_128" Value="M3" MCT="3"/>
			<Cell CellID="R_128" Value="0" MCT="4"/>
			<Cell CellID="U_128" Value="0" MCT="5"/>
			<Cell CellID="Z_128" Value="35.0000" MCT="6"/>
			<Cell CellID="AC_128" Value="0" MCT="7"/>
			<Cell CellID="AI_128" Value="0" MCT="9"/>
			<Cell CellID="AF_128" Value="0" MCT="8" Receive="0"/>
			<Cell CellID="AM_128" Value="0" MCT="10" Receive="0"/>
		</Cells>
		<Cells>
			<Cell CellID="D_129" FirstCell="1" Value="070102b" MCT="2"/>
			<Cell CellID="O_129" Value="M3" MCT="3"/>
			<Cell CellID="R_129" Value="0" MCT="4"/>
			<Cell CellID="U_129" Value="0" MCT="5"/>
			<Cell CellID="Z_129" Value="30.0000" MCT="6"/>
			<Cell CellID="AC_129" Value="0" MCT="7"/>
			<Cell CellID="AI_129" Value="0" MCT="9"/>
			<Cell CellID="AF_129" Value="0" MCT="8" Receive="0"/>
			<Cell CellID="AM_129" Value="0" MCT="10" Receive="0"/>
		</Cells>
		<Cells>
			<Cell CellID="D_130" FirstCell="1" Value="070103a" MCT="2"/>
			<Cell CellID="O_130" Value="M3" MCT="3"/>
			<Cell CellID="R_130" Value="0" MCT="4"/>
			<Cell CellID="U_130" Value="0" MCT="5"/>
			<Cell CellID="Z_130" Value="30.0000" MCT="6"/>
			<Cell CellID="AC_130" Value="0" MCT="7"/>
			<Cell CellID="AI_130" Value="0" MCT="9"/>
			<Cell CellID="AF_130" Value="0" MCT="8" Receive="0"/>
			<Cell CellID="AM_130" Value="0" MCT="10" Receive="0"/>
		</Cells>
		<Cells>
			<Cell CellID="D_131" FirstCell="1" Value="070103b" MCT="2"/>
			<Cell CellID="O_131" Value="M3" MCT="3"/>
			<Cell CellID="R_131" Value="0" MCT="4"/>
			<Cell CellID="U_131" Value="0" MCT="5"/>
			<Cell CellID="Z_131" Value="20.0000" MCT="6"/>
			<Cell CellID="AC_131" Value="0" MCT="7"/>
			<Cell CellID="AI_131" Value="0" MCT="9"/>
			<Cell CellID="AF_131" Value="0" MCT="8" Receive="0"/>
			<Cell CellID="AM_131" Value="0" MCT="10" Receive="0"/>
		</Cells>
		<Cells>
			<Cell CellID="D_132" FirstCell="1" Value="070104a" MCT="2"/>
			<Cell CellID="O_132" Value="M3" MCT="3"/>
			<Cell CellID="R_132" Value="0" MCT="4"/>
			<Cell CellID="U_132" Value="0" MCT="5"/>
			<Cell CellID="Z_132" Value="25.0000" MCT="6"/>
			<Cell CellID="AC_132" Value="0" MCT="7"/>
			<Cell CellID="AI_132" Value="0" MCT="9"/>
			<Cell CellID="AF_132" Value="0" MCT="8" Receive="0"/>
			<Cell CellID="AM_132" Value="0" MCT="10" Receive="0"/>
		</Cells>
		<Cells>
			<Cell CellID="D_133" FirstCell="1" Value="070104b" MCT="2"/>
			<Cell CellID="O_133" Value="M3" MCT="3"/>
			<Cell CellID="R_133" Value="0" MCT="4"/>
			<Cell CellID="U_133" Value="0" MCT="5"/>
			<Cell CellID="Z_133" Value="15.0000" MCT="6"/>
			<Cell CellID="AC_133" Value="0" MCT="7"/>
			<Cell CellID="AI_133" Value="0" MCT="9"/>
			<Cell CellID="AF_133" Value="0" MCT="8" Receive="0"/>
			<Cell CellID="AM_133" Value="0" MCT="10" Receive="0"/>
		</Cells>
		<Cells>
			<Cell CellID="D_134" FirstCell="1" Value="070601a" MCT="2"/>
			<Cell CellID="O_134" Value="M3" MCT="3"/>
			<Cell CellID="R_134" Value="0" MCT="4"/>
			<Cell CellID="U_134" Value="0" MCT="5"/>
			<Cell CellID="Z_134" Value="15.0000" MCT="6"/>
			<Cell CellID="AC_134" Value="0" MCT="7"/>
			<Cell CellID="AI_134" Value="0" MCT="9"/>
			<Cell CellID="AF_134" Value="0" MCT="8" Receive="0"/>
			<Cell CellID="AM_134" Value="0" MCT="10" Receive="0"/>
		</Cells>
		<Cells>
			<Cell CellID="D_135" FirstCell="1" Value="070601b" MCT="2"/>
			<Cell CellID="O_135" Value="M3" MCT="3"/>
			<Cell CellID="R_135" Value="0" MCT="4"/>
			<Cell CellID="U_135" Value="0" MCT="5"/>
			<Cell CellID="Z_135" Value="10.0000" MCT="6"/>
			<Cell CellID="AC_135" Value="0" MCT="7"/>
			<Cell CellID="AI_135" Value="0" MCT="9"/>
			<Cell CellID="AF_135" Value="0" MCT="8" Receive="0"/>
			<Cell CellID="AM_135" Value="0" MCT="10" Receive="0"/>
		</Cells>
		<Cells>
			<Cell CellID="D_136" FirstCell="1" Value="070602a" MCT="2"/>
			<Cell CellID="O_136" Value="M3" MCT="3"/>
			<Cell CellID="R_136" Value="0" MCT="4"/>
			<Cell CellID="U_136" Value="0" MCT="5"/>
			<Cell CellID="Z_136" Value="5.0000" MCT="6"/>
			<Cell CellID="AC_136" Value="0" MCT="7"/>
			<Cell CellID="AI_136" Value="0" MCT="9"/>
			<Cell CellID="AF_136" Value="0" MCT="8" Receive="0"/>
			<Cell CellID="AM_136" Value="0" MCT="10" Receive="0"/>
		</Cells>
		<Cells>
			<Cell CellID="D_137" FirstCell="1" Value="070602b" MCT="2"/>
			<Cell CellID="O_137" Value="M3" MCT="3"/>
			<Cell CellID="R_137" Value="0" MCT="4"/>
			<Cell CellID="U_137" Value="0" MCT="5"/>
			<Cell CellID="Z_137" Value="5.0000" MCT="6"/>
			<Cell CellID="AC_137" Value="0" MCT="7"/>
			<Cell CellID="AI_137" Value="0" MCT="9"/>
			<Cell CellID="AF_137" Value="0" MCT="8" Receive="0"/>
			<Cell CellID="AM_137" Value="0" MCT="10" Receive="0"/>
		</Cells>
		<Cells>
			<Cell CellID="D_138" FirstCell="1" Value="0707" MCT="2"/>
			<Cell CellID="O_138" Value="M3" MCT="3"/>
			<Cell CellID="R_138" Value="0" MCT="4"/>
			<Cell CellID="U_138" Value="0" MCT="5"/>
			<Cell CellID="Z_138" Value="10.0000" MCT="6"/>
			<Cell CellID="AC_138" Value="0" MCT="7"/>
			<Cell CellID="AI_138" Value="0" MCT="9"/>
			<Cell CellID="AF_138" Value="0" MCT="8" Receive="0"/>
			<Cell CellID="AM_138" Value="0" MCT="10" Receive="0"/>
		</Cells>
		<Cells>
			<Cell CellID="D_139" FirstCell="1" Value="070801" MCT="2"/>
			<Cell CellID="O_139" Value="Kg" MCT="3"/>
			<Cell CellID="R_139" Value="0" MCT="4"/>
			<Cell CellID="U_139" Value="0" MCT="5"/>
			<Cell CellID="Z_139" Value="25.0000" MCT="6"/>
			<Cell CellID="AC_139" Value="0" MCT="7"/>
			<Cell CellID="AI_139" Value="0" MCT="9"/>
			<Cell CellID="AF_139" Value="0" MCT="8" Receive="0"/>
			<Cell CellID="AM_139" Value="0" MCT="10" Receive="0"/>
		</Cells>
		<Cells>
			<Cell CellID="D_140" FirstCell="1" Value="070802" MCT="2"/>
			<Cell CellID="O_140" Value="Kg" MCT="3"/>
			<Cell CellID="R_140" Value="0" MCT="4"/>
			<Cell CellID="U_140" Value="0" MCT="5"/>
			<Cell CellID="Z_140" Value="10.0000" MCT="6"/>
			<Cell CellID="AC_140" Value="0" MCT="7"/>
			<Cell CellID="AI_140" Value="0" MCT="9"/>
			<Cell CellID="AF_140" Value="0" MCT="8" Receive="0"/>
			<Cell CellID="AM_140" Value="0" MCT="10" Receive="0"/>
		</Cells>
		<Cells>
			<Cell CellID="D_141" FirstCell="1" Value="070803" MCT="2"/>
			<Cell CellID="O_141" Value="Kg" MCT="3"/>
			<Cell CellID="R_141" Value="0" MCT="4"/>
			<Cell CellID="U_141" Value="0" MCT="5"/>
			<Cell CellID="Z_141" Value="5.0000" MCT="6"/>
			<Cell CellID="AC_141" Value="0" MCT="7"/>
			<Cell CellID="AI_141" Value="0" MCT="9"/>
			<Cell CellID="AF_141" Value="0" MCT="8" Receive="0"/>
			<Cell CellID="AM_141" Value="0" MCT="10" Receive="0"/>
		</Cells>
		<Cells>
			<Cell CellID="D_142" FirstCell="1" Value="0709" MCT="2"/>
			<Cell CellID="O_142" Value="Kg" MCT="3"/>
			<Cell CellID="R_142" Value="0" MCT="4"/>
			<Cell CellID="U_142" Value="0" MCT="5"/>
			<Cell CellID="Z_142" Value="5.0000" MCT="6"/>
			<Cell CellID="AC_142" Value="0" MCT="7"/>
			<Cell CellID="AI_142" Value="0" MCT="9"/>
			<Cell CellID="AF_142" Value="0" MCT="8" Receive="0"/>
			<Cell CellID="AM_142" Value="0" MCT="10" Receive="0"/>
		</Cells>
		<Cells>
			<Cell CellID="D_143" FirstCell="1" Value="0801" MCT="2"/>
			<Cell CellID="O_143" Value="Kg" MCT="3"/>
			<Cell CellID="R_143" Value="0" MCT="4"/>
			<Cell CellID="U_143" Value="0" MCT="5"/>
			<Cell CellID="Z_143" Value="10.0000" MCT="6"/>
			<Cell CellID="AC_143" Value="0" MCT="7"/>
			<Cell CellID="AI_143" Value="0" MCT="9"/>
			<Cell CellID="AF_143" Value="0" MCT="8" Receive="0"/>
			<Cell CellID="AM_143" Value="0" MCT="10" Receive="0"/>
		</Cells>
		<Cells>
			<Cell CellID="D_144" FirstCell="1" Value="0802" MCT="2"/>
			<Cell CellID="O_144" Value="Kg" MCT="3"/>
			<Cell CellID="R_144" Value="0" MCT="4"/>
			<Cell CellID="U_144" Value="0" MCT="5"/>
			<Cell CellID="Z_144" Value="2.0000" MCT="6"/>
			<Cell CellID="AC_144" Value="0" MCT="7"/>
			<Cell CellID="AI_144" Value="0" MCT="9"/>
			<Cell CellID="AF_144" Value="0" MCT="8" Receive="0"/>
			<Cell CellID="AM_144" Value="0" MCT="10" Receive="0"/>
		</Cells>
		<Cells>
			<Cell CellID="D_145" FirstCell="1" Value="0901" MCT="2"/>
			<Cell CellID="O_145" Value="M3" MCT="3"/>
			<Cell CellID="R_145" Value="0" MCT="4"/>
			<Cell CellID="U_145" Value="0" MCT="5"/>
			<Cell CellID="Z_145" Value="8.0000" MCT="6"/>
			<Cell CellID="AC_145" Value="0" MCT="7"/>
			<Cell CellID="AI_145" Value="0" MCT="9"/>
			<Cell CellID="AF_145" Value="0" MCT="8" Receive="0"/>
			<Cell CellID="AM_145" Value="0" MCT="10" Receive="0"/>
		</Cells>
		<Cells>
			<Cell CellID="D_146" FirstCell="1" Value="0902" MCT="2"/>
			<Cell CellID="O_146" Value="KW/h" MCT="3"/>
			<Cell CellID="R_146" Value="0" MCT="4"/>
			<Cell CellID="U_146" Value="0" MCT="5"/>
			<Cell CellID="Z_146" Value="2.0000" MCT="6"/>
			<Cell CellID="AC_146" Value="0" MCT="7"/>
			<Cell CellID="AI_146" Value="0" MCT="9"/>
			<Cell CellID="AF_146" Value="0" MCT="8" Receive="0"/>
			<Cell CellID="AM_146" Value="0" MCT="10" Receive="0"/>
		</Cells>
		<Cells>
			<Cell CellID="D_147" FirstCell="1" Value="09030101" MCT="2"/>
			<Cell CellID="O_147" Value="M3" MCT="3"/>
			<Cell CellID="R_147" Value="0" MCT="4"/>
			<Cell CellID="U_147" Value="0" MCT="5"/>
			<Cell CellID="Z_147" Value="3.0000" MCT="6"/>
			<Cell CellID="AC_147" Value="0" MCT="7"/>
			<Cell CellID="AI_147" Value="0" MCT="9"/>
			<Cell CellID="AF_147" Value="0" MCT="8" Receive="0"/>
			<Cell CellID="AM_147" Value="0" MCT="10" Receive="0"/>
		</Cells>
		<Cells>
			<Cell CellID="D_148" FirstCell="1" Value="09030102" MCT="2"/>
			<Cell CellID="O_148" Value="M3" MCT="3"/>
			<Cell CellID="R_148" Value="0" MCT="4"/>
			<Cell CellID="U_148" Value="0" MCT="5"/>
			<Cell CellID="Z_148" Value="5.0000" MCT="6"/>
			<Cell CellID="AC_148" Value="0" MCT="7"/>
			<Cell CellID="AI_148" Value="0" MCT="9"/>
			<Cell CellID="AF_148" Value="0" MCT="8" Receive="0"/>
			<Cell CellID="AM_148" Value="0" MCT="10" Receive="0"/>
		</Cells>
		<Cells>
			<Cell CellID="D_149" FirstCell="1" Value="09030201" MCT="2"/>
			<Cell CellID="O_149" Value="M3" MCT="3"/>
			<Cell CellID="R_149" Value="0" MCT="4"/>
			<Cell CellID="U_149" Value="0" MCT="5"/>
			<Cell CellID="Z_149" Value="1.0000" MCT="6"/>
			<Cell CellID="AC_149" Value="0" MCT="7"/>
			<Cell CellID="AI_149" Value="0" MCT="9"/>
			<Cell CellID="AF_149" Value="0" MCT="8" Receive="0"/>
			<Cell CellID="AM_149" Value="0" MCT="10" Receive="0"/>
		</Cells>
		<Cells>
			<Cell CellID="D_150" FirstCell="1" Value="09030202a" MCT="2"/>
			<Cell CellID="O_150" Value="M3" MCT="3"/>
			<Cell CellID="R_150" Value="0" MCT="4"/>
			<Cell CellID="U_150" Value="0" MCT="5"/>
			<Cell CellID="Z_150" Value="2.0000" MCT="6"/>
			<Cell CellID="AC_150" Value="0" MCT="7"/>
			<Cell CellID="AI_150" Value="0" MCT="9"/>
			<Cell CellID="AF_150" Value="0" MCT="8" Receive="0"/>
			<Cell CellID="AM_150" Value="0" MCT="10" Receive="0"/>
		</Cells>
		<Cells>
			<Cell CellID="D_151" FirstCell="1" Value="09030202b" MCT="2"/>
			<Cell CellID="O_151" Value="M3" MCT="3"/>
			<Cell CellID="R_151" Value="0" MCT="4"/>
			<Cell CellID="U_151" Value="0" MCT="5"/>
			<Cell CellID="Z_151" Value="3.0000" MCT="6"/>
			<Cell CellID="AC_151" Value="0" MCT="7"/>
			<Cell CellID="AI_151" Value="0" MCT="9"/>
			<Cell CellID="AF_151" Value="0" MCT="8" Receive="0"/>
			<Cell CellID="AM_151" Value="0" MCT="10" Receive="0"/>
		</Cells>
		<Cells>
			<Cell CellID="D_152" FirstCell="1" Value="09040101a" MCT="2"/>
			<Cell CellID="O_152" Value="M3" MCT="3"/>
			<Cell CellID="R_152" Value="0" MCT="4"/>
			<Cell CellID="U_152" Value="0" MCT="5"/>
			<Cell CellID="Z_152" Value="3.0000" MCT="6"/>
			<Cell CellID="AC_152" Value="0" MCT="7"/>
			<Cell CellID="AI_152" Value="0" MCT="9"/>
			<Cell CellID="AF_152" Value="0" MCT="8" Receive="0"/>
			<Cell CellID="AM_152" Value="0" MCT="10" Receive="0"/>
		</Cells>
		<Cells>
			<Cell CellID="D_153" FirstCell="1" Value="09040101b" MCT="2"/>
			<Cell CellID="O_153" Value="M3" MCT="3"/>
			<Cell CellID="R_153" Value="0" MCT="4"/>
			<Cell CellID="U_153" Value="0" MCT="5"/>
			<Cell CellID="Z_153" Value="3.0000" MCT="6"/>
			<Cell CellID="AC_153" Value="0" MCT="7"/>
			<Cell CellID="AI_153" Value="0" MCT="9"/>
			<Cell CellID="AF_153" Value="0" MCT="8" Receive="0"/>
			<Cell CellID="AM_153" Value="0" MCT="10" Receive="0"/>
		</Cells>
		<Cells>
			<Cell CellID="D_154" FirstCell="1" Value="09040102a" MCT="2"/>
			<Cell CellID="O_154" Value="M3" MCT="3"/>
			<Cell CellID="R_154" Value="0" MCT="4"/>
			<Cell CellID="U_154" Value="0" MCT="5"/>
			<Cell CellID="Z_154" Value="5.0000" MCT="6"/>
			<Cell CellID="AC_154" Value="0" MCT="7"/>
			<Cell CellID="AI_154" Value="0" MCT="9"/>
			<Cell CellID="AF_154" Value="0" MCT="8" Receive="0"/>
			<Cell CellID="AM_154" Value="0" MCT="10" Receive="0"/>
		</Cells>
		<Cells>
			<Cell CellID="D_155" FirstCell="1" Value="09040102b" MCT="2"/>
			<Cell CellID="O_155" Value="M3" MCT="3"/>
			<Cell CellID="R_155" Value="0" MCT="4"/>
			<Cell CellID="U_155" Value="0" MCT="5"/>
			<Cell CellID="Z_155" Value="6.0000" MCT="6"/>
			<Cell CellID="AC_155" Value="0" MCT="7"/>
			<Cell CellID="AI_155" Value="0" MCT="9"/>
			<Cell CellID="AF_155" Value="0" MCT="8" Receive="0"/>
			<Cell CellID="AM_155" Value="0" MCT="10" Receive="0"/>
		</Cells>
		<Cells>
			<Cell CellID="D_156" FirstCell="1" Value="09040201a" MCT="2"/>
			<Cell CellID="O_156" Value="M3" MCT="3"/>
			<Cell CellID="R_156" Value="0" MCT="4"/>
			<Cell CellID="U_156" Value="0" MCT="5"/>
			<Cell CellID="Z_156" Value="3.0000" MCT="6"/>
			<Cell CellID="AC_156" Value="0" MCT="7"/>
			<Cell CellID="AI_156" Value="0" MCT="9"/>
			<Cell CellID="AF_156" Value="0" MCT="8" Receive="0"/>
			<Cell CellID="AM_156" Value="0" MCT="10" Receive="0"/>
		</Cells>
		<Cells>
			<Cell CellID="D_157" FirstCell="1" Value="09040201b" MCT="2"/>
			<Cell CellID="O_157" Value="M3" MCT="3"/>
			<Cell CellID="R_157" Value="0" MCT="4"/>
			<Cell CellID="U_157" Value="0" MCT="5"/>
			<Cell CellID="Z_157" Value="1.0000" MCT="6"/>
			<Cell CellID="AC_157" Value="0" MCT="7"/>
			<Cell CellID="AI_157" Value="0" MCT="9"/>
			<Cell CellID="AF_157" Value="0" MCT="8" Receive="0"/>
			<Cell CellID="AM_157" Value="0" MCT="10" Receive="0"/>
		</Cells>
		<Cells>
			<Cell CellID="D_158" FirstCell="1" Value="09040202a" MCT="2"/>
			<Cell CellID="O_158" Value="M3" MCT="3"/>
			<Cell CellID="R_158" Value="0" MCT="4"/>
			<Cell CellID="U_158" Value="0" MCT="5"/>
			<Cell CellID="Z_158" Value="4.0000" MCT="6"/>
			<Cell CellID="AC_158" Value="0" MCT="7"/>
			<Cell CellID="AI_158" Value="0" MCT="9"/>
			<Cell CellID="AF_158" Value="0" MCT="8" Receive="0"/>
			<Cell CellID="AM_158" Value="0" MCT="10" Receive="0"/>
		</Cells>
		<Cells>
			<Cell CellID="D_159" FirstCell="1" Value="09040202b" MCT="2"/>
			<Cell CellID="O_159" Value="M3" MCT="3"/>
			<Cell CellID="R_159" Value="0" MCT="4"/>
			<Cell CellID="U_159" Value="0" MCT="5"/>
			<Cell CellID="Z_159" Value="3.0000" MCT="6"/>
			<Cell CellID="AC_159" Value="0" MCT="7"/>
			<Cell CellID="AI_159" Value="0" MCT="9"/>
			<Cell CellID="AF_159" Value="0" MCT="8" Receive="0"/>
			<Cell CellID="AM_159" Value="0" MCT="10" Receive="0"/>
		</Cells>
		<Cells>
			<Cell CellID="D_160" FirstCell="1" Value="0702" MCT="2"/>
			<Cell CellID="O_160" Value="M3" MCT="3"/>
			<Cell CellID="R_160" Value="0" MCT="4"/>
			<Cell CellID="U_160" Value="0" MCT="5"/>
			<Cell CellID="Z_160" Value="20.0000" MCT="6"/>
			<Cell CellID="AC_160" Value="0" MCT="7"/>
			<Cell CellID="AI_160" Value="0" MCT="9"/>
			<Cell CellID="AF_160" Value="0" MCT="8" Receive="0"/>
			<Cell CellID="AM_160" Value="0" MCT="10" Receive="0"/>
		</Cells>
		<Cells>
			<Cell CellID="D_161" FirstCell="1" Value="0703" MCT="2"/>
			<Cell CellID="O_161" Value="M3" MCT="3"/>
			<Cell CellID="R_161" Value="0" MCT="4"/>
			<Cell CellID="U_161" Value="0" MCT="5"/>
			<Cell CellID="Z_161" Value="20.0000" MCT="6"/>
			<Cell CellID="AC_161" Value="0" MCT="7"/>
			<Cell CellID="AI_161" Value="0" MCT="9"/>
			<Cell CellID="AF_161" Value="0" MCT="8" Receive="0"/>
			<Cell CellID="AM_161" Value="0" MCT="10" Receive="0"/>
		</Cells>
		<Cells>
			<Cell CellID="D_162" FirstCell="1" Value="0704" MCT="2"/>
			<Cell CellID="O_162" Value="M3" MCT="3"/>
			<Cell CellID="R_162" Value="0" MCT="4"/>
			<Cell CellID="U_162" Value="0" MCT="5"/>
			<Cell CellID="Z_162" Value="20.0000" MCT="6"/>
			<Cell CellID="AC_162" Value="0" MCT="7"/>
			<Cell CellID="AI_162" Value="0" MCT="9"/>
			<Cell CellID="AF_162" Value="0" MCT="8" Receive="0"/>
			<Cell CellID="AM_162" Value="0" MCT="10" Receive="0"/>
		</Cells>
		<Cells>
			<Cell CellID="D_163" FirstCell="1" Value="0705" MCT="2"/>
			<Cell CellID="O_163" Value="M3" MCT="3"/>
			<Cell CellID="R_163" Value="0" MCT="4"/>
			<Cell CellID="U_163" Value="0" MCT="5"/>
			<Cell CellID="Z_163" Value="20.0000" MCT="6"/>
			<Cell CellID="AC_163" Value="0" MCT="7"/>
			<Cell CellID="AI_163" Value="0" MCT="9"/>
			<Cell CellID="AF_163" Value="0" MCT="8" Receive="0"/>
			<Cell CellID="AM_163" Value="0" MCT="10" Receive="0"/>
		</Cells>
		<Cells>
			<Cell CellID="D_164" FirstCell="1" Value="070901" MCT="2"/>
			<Cell CellID="O_164" Value="Kg" MCT="3"/>
			<Cell CellID="R_164" Value="0" MCT="4"/>
			<Cell CellID="U_164" Value="0" MCT="5"/>
			<Cell CellID="Z_164" Value="20.0000" MCT="6"/>
			<Cell CellID="AC_164" Value="0" MCT="7"/>
			<Cell CellID="AI_164" Value="0" MCT="9"/>
			<Cell CellID="AF_164" Value="0" MCT="8" Receive="0"/>
			<Cell CellID="AM_164" Value="0" MCT="10" Receive="0"/>
		</Cells>
		<Cells>
			<Cell CellID="D_165" FirstCell="1" Value="070902" MCT="2"/>
			<Cell CellID="O_165" Value="Kg" MCT="3"/>
			<Cell CellID="R_165" Value="0" MCT="4"/>
			<Cell CellID="U_165" Value="0" MCT="5"/>
			<Cell CellID="Z_165" Value="5.0000" MCT="6"/>
			<Cell CellID="AC_165" Value="0" MCT="7"/>
			<Cell CellID="AI_165" Value="0" MCT="9"/>
			<Cell CellID="AF_165" Value="0" MCT="8" Receive="0"/>
			<Cell CellID="AM_165" Value="0" MCT="10" Receive="0"/>
		</Cells>
		<Cells>
			<Cell CellID="D_166" FirstCell="1" Value="090301" MCT="2"/>
			<Cell CellID="O_166" Value="M3" MCT="3"/>
			<Cell CellID="R_166" Value="0" MCT="4"/>
			<Cell CellID="U_166" Value="0" MCT="5"/>
			<Cell CellID="Z_166" Value="3.0000" MCT="6"/>
			<Cell CellID="AC_166" Value="0" MCT="7"/>
			<Cell CellID="AI_166" Value="0" MCT="9"/>
			<Cell CellID="AF_166" Value="0" MCT="8" Receive="0"/>
			<Cell CellID="AM_166" Value="0" MCT="10" Receive="0"/>
		</Cells>
		<Cells>
			<Cell CellID="D_167" FirstCell="1" Value="09030301" MCT="2"/>
			<Cell CellID="O_167" Value="M3" MCT="3"/>
			<Cell CellID="R_167" Value="0" MCT="4"/>
			<Cell CellID="U_167" Value="0" MCT="5"/>
			<Cell CellID="Z_167" Value="0.5000" MCT="6"/>
			<Cell CellID="AC_167" Value="0" MCT="7"/>
			<Cell CellID="AI_167" Value="0" MCT="9"/>
			<Cell CellID="AF_167" Value="0" MCT="8" Receive="0"/>
			<Cell CellID="AM_167" Value="0" MCT="10" Receive="0"/>
		</Cells>
		<Cells>
			<Cell CellID="D_168" FirstCell="1" Value="09040301" MCT="2"/>
			<Cell CellID="O_168" Value="M3" MCT="3"/>
			<Cell CellID="R_168" Value="0" MCT="4"/>
			<Cell CellID="U_168" Value="0" MCT="5"/>
			<Cell CellID="Z_168" Value="0.0000" MCT="6"/>
			<Cell CellID="AC_168" Value="0" MCT="7"/>
			<Cell CellID="AI_168" Value="0" MCT="9"/>
			<Cell CellID="AF_168" Value="0" MCT="8" Receive="0"/>
			<Cell CellID="AM_168" Value="0" MCT="10" Receive="0"/>
		</Cells>
		<Cells>
			<Cell CellID="D_169" FirstCell="1" Value="09040302" MCT="2"/>
			<Cell CellID="O_169" Value="M3" MCT="3"/>
			<Cell CellID="R_169" Value="0" MCT="4"/>
			<Cell CellID="U_169" Value="0" MCT="5"/>
			<Cell CellID="Z_169" Value="0.5000" MCT="6"/>
			<Cell CellID="AC_169" Value="0" MCT="7"/>
			<Cell CellID="AI_169" Value="0" MCT="9"/>
			<Cell CellID="AF_169" Value="0" MCT="8" Receive="0"/>
			<Cell CellID="AM_169" Value="0" MCT="10" Receive="0"/>
		</Cells>
		<Cells>
			<Cell CellID="D_170" FirstCell="1" Value="1001a" MCT="2"/>
			<Cell CellID="O_170" Value="Kg" MCT="3"/>
			<Cell CellID="R_170" Value="0" MCT="4"/>
			<Cell CellID="U_170" Value="0" MCT="5"/>
			<Cell CellID="Z_170" Value="20.0000" MCT="6"/>
			<Cell CellID="AC_170" Value="0" MCT="7"/>
			<Cell CellID="AI_170" Value="0" MCT="9"/>
			<Cell CellID="AF_170" Value="0" MCT="8" Receive="0"/>
			<Cell CellID="AM_170" Value="0" MCT="10" Receive="0"/>
		</Cells>
		<Cells>
			<Cell CellID="D_171" FirstCell="1" Value="1101b" MCT="2"/>
			<Cell CellID="O_171" Value="Kg" MCT="3"/>
			<Cell CellID="R_171" Value="0" MCT="4"/>
			<Cell CellID="U_171" Value="0" MCT="5"/>
			<Cell CellID="Z_171" Value="10.0000" MCT="6"/>
			<Cell CellID="AC_171" Value="0" MCT="7"/>
			<Cell CellID="AI_171" Value="0" MCT="9"/>
			<Cell CellID="AF_171" Value="0" MCT="8" Receive="0"/>
			<Cell CellID="AM_171" Value="0" MCT="10" Receive="0"/>
		</Cells>
	</Section>
	<Section Dynamic="0" MaxRows="0">
		<Cells>
			<Cell CellID="AF_175" Value=""/>
			<Cell CellID="AF_176" Value="04/08/2010"/>
		</Cells>
	</Section>
</Sections>
