<!-- edited with XML Spy v4.1 U (http://www.xmlspy.com) by CMCSoft-->
<!DOCTYPE Sections SYSTEM "Schema.dtd">
<Sections>
	<Section Dynamic="0" MaxRows="0">
		<Cells>
			<Cell CellID="F_10" Value=""/>
			<Cell CellID="H_8" Value=""/>
			<Cell CellID="F_12" Value=""/>
			<Cell CellID="F_16" Value=""/>
			<Cell CellID="N_16" Value=""/>
			<Cell CellID="V_16" Value=""/>
			<Cell CellID="V_32" Value=""/>
			<Cell CellID="M_23" Value=""/>
			<Cell CellID="M_36" Value=""/>
			<Cell CellID="V_30" Value=""/>
			<Cell CellID="H_18" Value=""/>
			<Cell CellID="F_22" Value=""/>
			<Cell CellID="F_24" Value=""/>
			<Cell CellID="Q_24" Value=""/>
			<Cell CellID="F_26" Value=""/>
			<Cell CellID="N_26" Value=""/>
			<Cell CellID="V_26" Value=""/>
			<Cell CellID="N_28" Value=""/>
			<Cell CellID="V_34" Value=""/>
		</Cells>
	</Section>
	<Section Dynamic="1" MaxRows="0">
		<Cells>
			<Cell CellID="D_23" FirstCell="0" Value="x" MCT="1"/>
			<Cell CellID="D_24" Value="x" MCT="2"/>
			<Cell CellID="D_25" Value="" MCT="3"/>
			<Cell CellID="D_26" Value="" MCT="4"/>
			<Cell CellID="D_27" Value="" MCT="5"/>
			<Cell CellID="D_29" Value="x" MCT="6"/>
			<Cell CellID="D_30" Value="x" MCT="7"/>
			<Cell CellID="J_33" Value="dau tu 1" MCT="8"/>
			<Cell CellID="J_34" Value="dau tu 2" MCT="9"/>
			<Cell CellID="J_35" Value="dau tu 3" MCT="10"/>
			<Cell CellID="S_38" Value="01/01/2002" MCT="11"/>
			<Cell CellID="Q_41" Value="10.000" MCT="12"/>
			<Cell CellID="N_42" Value="2002" MCT="13"/>
			<Cell CellID="U_42" Value="2020" MCT="14"/>
			<Cell CellID="J_43" Value="18" MCT="15"/>
			<Cell CellID="Q_43" Value="2002" MCT="16"/>
			<Cell CellID="N_44" Value="2" MCT="17"/>
			<Cell CellID="U_44" Value="2002" MCT="18"/>
			<Cell CellID="X_49" Value="1000000000000" MCT="3.1"/>
			<Cell CellID="X_50" Value="100000000" MCT="3.2"/>
			<Cell CellID="X_51" Value="100000000" MCT="3.3"/>
			<Cell CellID="X_52" Value="10000" MCT="3.4"/>
			<Cell CellID="X_54" Value="2500" MCT="4.1"/>
			<Cell CellID="X_55" Value="1000" MCT="4.2"/>
			<Cell CellID="X_56" Value="1500" MCT="4.3"/>
			<Cell CellID="X_58" Value="10" MCT="5.1"/>
			<Cell CellID="X_59" Value="1000" MCT="5.2"/>
			<Cell CellID="X_60" Value="10" MCT="5.3"/>
			<Cell CellID="X_61" Value="100" MCT="5.4"/>
			<Cell CellID="X_48" Value="" Receive="0" MCT="3.0"/>
			<Cell CellID="X_53" Value="" Receive="0" MCT="4.0"/>
			<Cell CellID="X_57" Value="" Receive="0" MCT="5.0"/>
		</Cells>
	</Section>
</Sections>
