<PL01_3_GTGT>
	<XeOTo>
		<ChiTietSoLuongXeOTo>
			<SoLuongXe id="ID_11">
				<loaiXe></loaiXe>
				<dviTinh></dviTinh>
				<tongXeBRa>1</tongXeBRa>
				<xeBanRa>1</xeBanRa>
				<giaBan>1</giaBan>
				<ghiChu></ghiChu>
			</SoLuongXe>
		</ChiTietSoLuongXeOTo>
		<congTongXeBRa>1</congTongXeBRa>
		<congXeBRa>1</congXeBRa>
		<congGiaBan>1</congGiaBan>
	</XeOTo>
	<XeHaiBanh>
		<ChiTietSoLuongXeHaiBanh>
			<SoLuongXe id="ID_12">
				<loaiXe></loaiXe>
				<dviTinh></dviTinh>
				<tongXeBRa>1</tongXeBRa>
				<xeBanRa>1</xeBanRa>
				<giaBan>1</giaBan>
				<ghiChu></ghiChu>
			</SoLuongXe>
		</ChiTietSoLuongXeHaiBanh>
		<congTongXeBRa>1</congTongXeBRa>
		<congXeBRa>1</congXeBRa>
		<congGiaBan>1</congGiaBan>
	</XeHaiBanh>
	<congTongXeBRa>1</congTongXeBRa>
	<congXeBRa>1</congXeBRa>
	<congGiaBan>1</congGiaBan>
</PL01_3_GTGT>
