<PL01_3_GTGT>
	<ChiTietBangKeHH id="ID_16">
		<HopDongXuatKhau>
			<so></so>
			<ngay></ngay>
			<ngoaiTe></ngoaiTe>
			<dongVietNam></dongVietNam>
			<hinhThucThanhToanHDongXKhau></hinhThucThanhToanHDongXKhau>
			<thoiHanThanhToanHDongXKhau></thoiHanThanhToanHDongXKhau>
		</HopDongXuatKhau>
		<ToKhaiHHoaXKhau>
			<so></so>
			<ngay></ngay>
			<ngoaiTe></ngoaiTe>
			<dongVietNam></dongVietNam>
		</ToKhaiHHoaXKhau>
		<HoaDonXKhau>
			<so></so>
			<ngay></ngay>
			<ngoaiTe></ngoaiTe>
			<dongVietNam></dongVietNam>
		</HoaDonXKhau>
		<CTuTToanNganHang>
			<so></so>
			<ngay></ngay>
			<ngoaiTe></ngoaiTe>
			<dongVietNam></dongVietNam>
		</CTuTToanNganHang>
		<ChungTuThanhToanBuTru>
			<VBanXNhanVoiNNgoai>
				<so></so>
				<ngay></ngay>
				<ngoaiTe></ngoaiTe>
				<dongVietNam></dongVietNam>
			</VBanXNhanVoiNNgoai>
			<HDongNhapKhau>
				<so></so>
				<ngay></ngay>
				<ngoaiTe></ngoaiTe>
				<dongVietNam></dongVietNam>
			</HDongNhapKhau>
			<ToKhaiHHoaNhapKhau>
				<soTKhai></soTKhai>
				<ngayDKyTKhai></ngayDKyTKhai>
				<ngoaiTe></ngoaiTe>
				<dongVietNam></dongVietNam>
			</ToKhaiHHoaNhapKhau>
			<chungTuThanhToanBuTruKhac></chungTuThanhToanBuTruKhac>
		</ChungTuThanhToanBuTru>
		<ghiChu></ghiChu>
	</ChiTietBangKeHH>
	<taiLieuKhac></taiLieuKhac>
</PL01_3_GTGT>
