<?xml version="1.0" encoding="UTF-8"?>
<HSoThueDTu>
	<HSoKhaiThue>
		<TTinChung>
			<TTinDVu>
				<maDVu>String</maDVu>
				<tenDVu>token</tenDVu>
				<pbanDVu>String</pbanDVu>
				<ttinNhaCCapDVu>String</ttinNhaCCapDVu>
			</TTinDVu>
			<TTinTKhaiThue>
				<TKhaiThue>
					<maTKhai>String</maTKhai>
					<tenTKhai>token</tenTKhai>
					<moTaBMau>String</moTaBMau>
					<pbanTKhaiXML>String</pbanTKhaiXML>
					<loaiTKhai>C</loaiTKhai>
					<soLan>1</soLan>
					<KyKKhaiThue>
						<kieuKy>D</kieuKy>
						<kyKKhai>String</kyKKhai>
						<kyKKhaiTuNgay>String</kyKKhaiTuNgay>
						<kyKKhaiDenNgay>String</kyKKhaiDenNgay>
						<kyKKhaiTuThang>String</kyKKhaiTuThang>
						<kyKKhaiDenThang>String</kyKKhaiDenThang>
					</KyKKhaiThue>
					<maCQTNoiNop>String</maCQTNoiNop>
					<tenCQTNoiNop>token</tenCQTNoiNop>
					<ngayLapTKhai>String</ngayLapTKhai>
					<GiaHan>
						<maLyDoGiaHan>String</maLyDoGiaHan>
						<lyDoGiaHan>String</lyDoGiaHan>
					</GiaHan>
					<nguoiKy>String</nguoiKy>
					<ngayKy>1967-08-13</ngayKy>
					<nganhNgheKD>String</nganhNgheKD>
				</TKhaiThue>
				<NNT>
					<mst>0000000000</mst>
					<tenNNT>token</tenNNT>
					<dchiNNT>token</dchiNNT>
					<phuongXa>String</phuongXa>
					<maHuyenNNT>String</maHuyenNNT>
					<tenHuyenNNT>String</tenHuyenNNT>
					<maTinhNNT>String</maTinhNNT>
					<tenTinhNNT>String</tenTinhNNT>
					<dthoaiNNT>String</dthoaiNNT>
					<faxNNT>String</faxNNT>
					<emailNNT>String</emailNNT>
				</NNT>
				<DLyThue>
					<mstDLyThue>0000000000</mstDLyThue>
					<tenDLyThue>token</tenDLyThue>
					<dchiDLyThue>token</dchiDLyThue>
					<maHuyenDLyThue>String</maHuyenDLyThue>
					<tenHuyenDLyThue>String</tenHuyenDLyThue>
					<maTinhDLyThue>String</maTinhDLyThue>
					<tenTinhDLyThue>String</tenTinhDLyThue>
					<dthoaiDLyThue>String</dthoaiDLyThue>
					<faxDLyThue>String</faxDLyThue>
					<emailDLyThue>String</emailDLyThue>
					<soHDongDLyThue>String</soHDongDLyThue>
					<ngayKyHDDLyThue>1967-08-13</ngayKyHDDLyThue>
					<NVienDLy>
						<tenNVienDLyThue>token</tenNVienDLyThue>
						<cchiHNghe>String</cchiHNghe>
					</NVienDLy>
				</DLyThue>
			</TTinTKhaiThue>
		</TTinChung>
		<CTieuTKhaiChinh>
			<noiBCao>String</noiBCao>
			<ngayBCao>1967-08-13</ngayBCao>
			<ngayMatChayBLai>1967-08-13</ngayMatChayBLai>
			<BKeBLaiMatChay>
				<ChiTietBKeBLaiMatChay id="id">
					<mauSo>String</mauSo>
					<tenBLai>String</tenBLai>
					<kyHieu>String</kyHieu>
					<tuSoDenSo>String</tuSoDenSo>
					<soLuong>1</soLuong>
					<lienBLai>1</lienBLai>
					<ghiChu>String</ghiChu>
					<ktraLoaiBLai>String</ktraLoaiBLai>
				</ChiTietBKeBLaiMatChay>
			</BKeBLaiMatChay>
			<lyDoMatChayBLai>String</lyDoMatChayBLai>
			<donViNhanBCao>String</donViNhanBCao>
			<nguoiDaiDien>String</nguoiDaiDien>
		</CTieuTKhaiChinh>
		<PLuc/>
	</HSoKhaiThue>
</HSoThueDTu>
